Workbook

Sheet ReadMe
B1: DPDP COMPLIANCE FRAMEWORK
B2: OPERATIONAL GUIDE | READ THIS FIRST
B4: 1. WHAT IS THIS DOCUMENT & WHY IT EXISTS
C5: Document Identity | D5: This workbook is a complete, operationally-ready DPDP Compliance Framework built on India’s Digital Personal Data Protection Act, 2023 and the DPDP Rules, 2025. It is not a legal commentary or academic reference — it is a working instrument designed to be your organisation’s central compliance programme artefact from Day 1 through audit-readiness.
C6: Design Philosophy | D6: The framework bridges two gaps that commonly cause compliance programmes to stall: (a) the gap between legal interpretation and operational implementation, and (b) the gap between knowing what to do and knowing who does it, by when, and with what evidence. Every sheet in this workbook serves a distinct function in closing those gaps.
C7: Intended Users | D7: DPO / Privacy Office (primary owner) | CISO / InfoSec | Legal & Compliance | IT & Engineering leadership | HR leadership | Product & UX leads | Business Unit Heads | Procurement & Vendor Management | Board / Executive sponsors | External auditors (read-only for Assessment + Dashboard sheets).
C8: Scope & Coverage | D8: 73 primary compliance obligations across 12 categories with Control IDs, Priority tiers, DPDP Section mapping, and Penalty exposure (Assessment + Implementation) + 340 granular implementation-level controls (Granular Controls) + 55+ RACI-mapped control responsibilities + 26-question Express Evaluation for applicability determination + Live Compliance Dashboard with formula-driven KPIs pulling from the master tracker + Framework Guide with maturity model, lifecycle definitions, and BU bifurcation rules.
B10: 2. FRAMEWORK ARCHITECTURE — HOW THE SHEETS CONNECT
B11: The six sheets form a sequential, dependency-linked workflow. Each sheet feeds the next. Skipping sheets creates gaps that compound downstream. Follow the numbered sequence below.
B12: ❶ Express Evaluation | C12: ENTRY POINT. Determines which controls apply to your organisation. Drives everything downstream. Without this, teams implement controls that don’t apply — or worse, miss controls that do. | D12: OUTPUT: Completed evaluation with all 26 questions answered. Entity classification confirmed. Applicable domains identified.
B13: ❷ RACI Matrix | C13: OWNERSHIP LAYER. Assigns functional and business-unit responsibility to every control. Without clear ownership, controls remain orphaned and unimplemented. | D13: OUTPUT: Every control row has at least one ‘A’ (Accountable) and one ‘R’ (Responsible). BU columns populated if D6=Yes in Express Evaluation.
B14: ❸ Assessment + Implementation | C14: OPERATIONAL ENGINE. Enhanced with Control IDs, Categories (12 domains), Priority tiers (Critical/High/Medium/Low), DPDP Section references, and Max Penalty exposure. Assessment Area (cols K–O) captures current-state maturity. Implementation Area (cols P–U) drives remediation. Governance & Evidence (cols V–Y) tracks artefacts. Built-in Assessment Summary auto-calculates readiness by priority and category. | D14: OUTPUT: All 73 items assessed for current state. Gap descriptions documented. Action plans, owners, target dates, and budgets assigned for every non-compliant item.
B15: ❹ Granular Controls | C15: ENGINEERING LAYER. 340 discrete controls for teams building systems, configuring platforms, and writing policies. Each control now carries its own assessment and implementation tracking columns. | D15: OUTPUT: Granular controls filtered by applicability. Technical teams have specific, verifiable implementation targets.
B16: ❺ Compliance Dashboard | C16: GOVERNANCE VIEW. Formula-driven summary of programme health. Shows assessment status distribution, implementation progress, risk heat, and overall compliance/evidence readiness percentages. | D16: OUTPUT: Live dashboard reflecting real-time data from the Assessment + Implementation sheet. Board-reportable at any time.
B17: ❻ Framework Guide | C17: REFERENCE LAYER. Definitions, maturity model, lifecycle stages, RACI conventions, BU bifurcation guidance, and risk calibration. Consult when any term or concept is unclear. | D17: OUTPUT: Shared understanding across all stakeholders of what each term, status, and rating means.
B18: TIP | C18: Think of the sheets as layers of a pyramid: Express Evaluation is the foundation (scope), RACI is the structure (ownership), Assessment+Implementation is the operating floor (execution), Granular Controls are the building blocks (engineering), Dashboard is the roof (visibility), and the Guide is the blueprint (definitions).
B20: 3. STEP-BY-STEP EXECUTION PLAYBOOK — YOUR FIRST 30 DAYS
B21: Follow these steps in sequence. Each step has a defined owner, duration, and verifiable output. Do not proceed to the next step until the current step’s output is confirmed.
B22: STEP 1 | C22: ❶ COMPLETE THE EXPRESS EVALUATION (Sheet: Express Evaluation)
C23: WHAT: Convene a cross-functional kick-off with DPO, Legal, CISO, HR Head, and a senior business representative. Walk through all 26 questions across Sections A–D. Answer every question using the dropdown in Column E. Review the auto-computed Applicability Result in Column F and the mapped control domains in Column G.
C24: WHY: This is your compliance scope definition. Every subsequent sheet is filtered and prioritised based on these answers. An incorrect classification here (e.g., treating yourself as a standard DF when you’re an SDF) cascades into missed obligations across the entire programme.
C25: WHO: DPO / Privacy Office (facilitator) + Legal (classification advisor) + CISO (security scope) + HR (employment data) + Business Unit Heads (BU determination)
C26: DURATION: Half-day workshop (2–4 hours, including discussion and sign-off)
C27: OUTPUT: Signed-off Express Evaluation with all 26 responses. Entity classification documented. List of applicable control domains extracted for downstream filtering.
B28: >> | C28: Pro tip: Print or project the Express Evaluation during the kick-off. Make it a collaborative exercise, not a form-filling task. Disagreements at this stage are valuable — they surface scope ambiguities that would otherwise emerge as compliance gaps months later.
B30: STEP 2 | C30: ❷ CUSTOMISE THE RACI MATRIX (Sheet: RACI Matrix)
C31: WHAT: Using the Express Evaluation outputs, review each control row in the RACI Matrix. Confirm or adjust pre-populated RACI assignments to match your organisation’s actual structure. If Express Evaluation D6 = Yes (multiple BUs), populate the BU columns (M, N, O) with named roles from each business unit. Mark controls as ‘Not Applicable’ in the Risk Priority column if the Express Evaluation determined they’re out of scope.
C32: WHY: Without explicit ownership, controls exist on paper but not in practice. The RACI Matrix converts abstract obligations into named accountabilities. It also prevents the common failure mode where ‘everyone is responsible’ (meaning no one is).
C33: WHO: DPO / Privacy Office (orchestrator) + Each functional head confirms their ‘R’ and ‘A’ assignments + BU Heads nominate BU Privacy Champions and BU IT Leads
C34: DURATION: 1–2 working days (individual function reviews + one alignment meeting)
C35: OUTPUT: Fully customised RACI Matrix. Every applicable control has exactly one ‘A’ and at least one ‘R’. BU columns populated where applicable. Non-applicable controls marked.
B36: !! | C36: Common mistake: Assigning ‘A’ (Accountable) to more than one function per control. Accountability must be singular. If two functions share accountability, the control will fall between chairs during execution. Resolve dual-accountability during this step, not during an audit.
B38: STEP 3 | C38: ❸ CONDUCT BASELINE ASSESSMENT (Sheet: Assessment + Implementation — Assessment Area)
C39: WHAT: For each of the 73 compliance items, evaluate your current state using the Assessment Area columns (K–O). Set Assessment Status (Compliant / Partially Compliant / Non-Compliant / Not Assessed / Not Applicable). Set Maturity Level (L0–L4). Flag gaps in Column M. Describe each gap in Column N. Assign a Risk Rating (Critical / High / Medium / Low) in Column O based on enforcement exposure and operational impact.
C40: WHY: You cannot build a remediation plan without knowing your starting position. This step produces the gap register — the single most important artefact for programme planning, budgeting, and board reporting. It also immediately populates the Compliance Dashboard.
C41: WHO: DPO leads assessment + CISO assesses security controls (Items 12–17) + Legal assesses consent/notice/rights (Items 1–5, 56–62) + IT assesses technical controls + HR assesses employment controls
C42: DURATION: 1–2 weeks (assessment interviews, evidence collection, gap documentation)
C43: OUTPUT: Completed Assessment Area for all 73 items. Gap register with risk ratings. Dashboard showing current compliance posture. Board-ready baseline report.
B44: TIP | C44: Assess honestly. The temptation is to mark items as ‘Partially Compliant’ when they are closer to ‘Non-Compliant’. Use L0–L4 maturity as a forcing function: if no documented policy or procedure exists, it’s L0 (Absent), regardless of informal practices. Auditors will test against documented, verifiable evidence — not tribal knowledge.
B46: STEP 4 | C46: ❹ BUILD THE IMPLEMENTATION PLAN (Sheet: Assessment + Implementation — Implementation Area)
C47: WHAT: For every item where Assessment Status is Non-Compliant or Partially Compliant, complete the Implementation Area columns (P–U). Set Implementation Status. Assign Accountable Owner (by name, not just function — cross-reference the RACI Matrix). Set Target Date. Write a specific Action Plan in Column S describing what needs to be built, configured, documented, or procured. Estimate budget in Column T. Set initial % Complete.
C48: WHY: This converts the gap register into an executable project plan. Without named owners, specific actions, and deadlines, gaps remain documented but unresolved. This step is where compliance transitions from assessment to implementation.
C49: WHO: DPO / Programme Manager builds the plan + Each Accountable Owner validates feasibility, timeline, and budget + CFO/Finance reviews budget estimates + Executive sponsor approves the consolidated plan
C50: DURATION: 3–5 working days (plan drafting + owner validation + executive sign-off)
C51: OUTPUT: Completed Implementation Area for all gap items. Named owners. Realistic target dates. Specific, verifiable action plans. Approved budget. Dashboard reflecting implementation trajectory.
B52: >> | C52: Link action plans to specific deliverables, not activities. ‘Implement consent mechanism’ is an activity. ‘Deploy consent SDK on web + mobile with granular purpose selection, withdrawal parity, and timestamped logging — tested and in production’ is a deliverable. The latter is auditable; the former is not.
B54: STEP 5 | C54: ❺ DEPLOY GRANULAR CONTROLS TO ENGINEERING & PROCESS TEAMS (Sheet: Granular Controls)
C55: WHAT: Filter the 340 granular controls by Applicability (referencing Express Evaluation results). Distribute relevant control sub-sets to owning teams: A-series (consent, notice, UI/UX) to Product + Legal, B-series (lawful processing, employment, biometrics) to Legal + HR + IT, C-series (security, breach) to CISO + IT. Each team assesses and tracks their controls using Columns H–N.
C56: WHY: The Compliance Worksheet (73 items) tells you what to comply with. The Granular Controls tell engineering and process teams exactly how. This is the bridge between compliance language and system configuration, code changes, and process documentation.
C57: WHO: DPO distributes filtered control sets + Product/Engineering owns A-series implementation + CISO/IT owns C-series + Legal + HR + Ops own B-series + Each team updates their tracking columns weekly
C58: DURATION: Ongoing (initial distribution: 1–2 days; tracking: continuous)
C59: OUTPUT: Filtered, assigned granular control registers. Teams have specific, verifiable implementation targets. Weekly status updates flow into programme tracking.
B61: STEP 6 | C61: ❻ ESTABLISH EVIDENCE COLLECTION & GOVERNANCE CADENCE (Sheets: Assessment + Implementation, Dashboard)
C62: WHAT: For each compliance item, populate the Governance columns (V–Y): set Evidence Status (Not Collected through Audit-Ready), record evidence artefact location (document IDs, repository links, system references) in Column W, set review cadence in Column X, and capture reviewer observations in Column Y. Establish a recurring governance rhythm: weekly implementation standups, monthly compliance reviews, quarterly board reporting using the Dashboard.
C63: WHY: Compliance without evidence is assertion without proof. Regulators and auditors will not accept stated compliance — they will test against documented, retrievable, timestamped evidence. The governance cadence ensures the framework remains a living instrument, not a one-time exercise.
C64: WHO: DPO / Programme Manager establishes cadence + Each Accountable Owner maintains their evidence + Internal Audit validates evidence quality + Board / Executive reviews Dashboard quarterly
C65: DURATION: Setup: 1 week | Ongoing: weekly standups (30 min), monthly reviews (2 hrs), quarterly board report (1 hr prep)
C66: OUTPUT: Evidence register populated. Artefact locations documented. Governance calendar established. Dashboard reporting to board on defined cadence. Audit-readiness trajectory visible.
B67: !! | C67: Do not wait until implementation is complete to start evidence collection. Evidence should be generated as a by-product of implementation, not retrospectively assembled before an audit. Configure systems to produce evidence automatically: timestamped consent logs, access control reports, breach simulation records, training completion certificates.
B69: 4. RECOMMENDED GOVERNANCE CADENCE
B70: Frequency | C70: Activity | Participants | Duration | D70: Purpose & Key Activities
B71: Weekly | C71: Implementation Standup DPO + Control Owners 15–30 min | D71: Review implementation status changes. Unblock dependencies. Update % Complete. Flag risks escalating from Medium to High/Critical.
B72: Fortnightly | C72: Evidence Review DPO + Internal Audit 1 hour | D72: Validate evidence quality for recently completed controls. Transition Evidence Status from ‘Collected’ to ‘Validated’. Identify evidence gaps early.
B73: Monthly | C73: Programme Review DPO + All Function Heads 2 hours | D73: Full programme health review using Dashboard. Assess assessment-to-implementation conversion rate. Review risk distribution trends. Reallocate resources if needed.
B74: Quarterly | C74: Board / Executive Report DPO + Exec Sponsor 1 hour | D74: Present Dashboard KPIs to Board. Compliance Rate %, Implementation Rate %, Evidence Readiness %, Critical/High gaps open. Seek decisions on budget, timeline, or scope changes.
B75: Annually | C75: Full Reassessment DPO + External Auditor 2–4 weeks | D75: Complete fresh baseline assessment. Re-run Express Evaluation (entity/processing scope may have changed). Engage independent auditor for SDF obligations (DPIA + Audit per Rule 13).
B77: 5. COMMON PITFALLS & HOW TO AVOID THEM
B78: ⚠ | C78: Skipping the Express Evaluation PROBLEM: Teams jump directly to the Assessment or RACI sheets without determining applicability. This leads to wasted effort on non-applicable controls and missed obligations on applicable ones. | D78: SOLUTION: Always start with Express Evaluation. Treat it as a mandatory gate before any other sheet is touched.
B79: ⚠ | C79: Assessing without implementing PROBLEM: The Assessment Area is completed with detailed gap descriptions, but the Implementation Area remains empty. The gap register becomes a static document rather than a project plan. | D79: SOLUTION: Pair every assessment session with an implementation planning session. Never document a gap without simultaneously assigning an owner and target date.
B80: ⚠ | C80: Generic RACI assignments PROBLEM: RACI is completed with function names (‘IT’, ‘Legal’) but no individual names. When escalation is needed, there’s no one to escalate to. | D80: SOLUTION: Append individual names to function assignments. ‘CISO — [Name]’ is accountable; ‘InfoSec’ is not.
B81: ⚠ | C81: Evidence as an afterthought PROBLEM: Controls are implemented but evidence is not collected during implementation. When audit arrives, teams scramble to reconstruct evidence retrospectively. | D81: SOLUTION: Build evidence generation into the implementation process itself. If a control requires ‘timestamped consent logs’, the implementation must include the logging mechanism, not just the consent UI.
B82: ⚠ | C82: Treating this as a one-time exercise PROBLEM: Framework is completed, filed, and forgotten. Six months later, new processing activities have been launched without compliance assessment. | D82: SOLUTION: Establish the governance cadence in Section 4. Integrate the Express Evaluation into your change management process: any new product, feature, vendor, or data flow triggers a reassessment.
B83: ⚠ | C83: Ignoring Business Unit bifurcation PROBLEM: Central team completes compliance for HQ but BU-specific processing activities (different products, geographies, customer segments) are missed. | D83: SOLUTION: If your organisation has multiple BUs processing personal data independently, BU columns must be active. Each BU needs a named Privacy Champion embedded in the BU.
B84: ⚠ | C84: Over-indexing on Granular Controls PROBLEM: Teams attempt to implement all 340 granular controls simultaneously, overwhelming engineering capacity. | D84: SOLUTION: Use the Granular Controls sheet selectively. Filter by applicability first (Express Evaluation), then prioritise by risk rating (Critical and High first). The 73-item Compliance Worksheet is your programme backbone; Granular Controls are the engineering detail layer.
B86: 6. QUICK-START PATHS — WHERE TO BEGIN BASED ON YOUR ROLE
B87: DPO / Privacy Officer | C87: You own this framework. Start with Express Evaluation (facilitate the kick-off), then customise the RACI Matrix, lead the baseline Assessment, build the Implementation Plan, and own the governance cadence. Your primary operating sheets are Assessment + Implementation and Dashboard.
B88: CISO / InfoSec Lead | C88: Your domain is Items 12–17 (Security Safeguards), Items 18–23 (Breach Notification), and the C1/C1.1 series in Granular Controls. Start by assessing current security posture against Rule 6(a)–(g). Build breach notification playbook against Rule 7. Own evidence for encryption, ACL, logging, backup, and monitoring controls.
B89: Legal & Compliance Head | C89: Your domain spans consent validity (Items 1–5), notice compliance (Rule 3/4), children’s data exemptions (Items 33–48), cross-border transfer (Items 64–65), and rights framework (Items 56–62). Validate legal basis classification in the RACI Matrix. Own the legal-privacy position for each control.
B90: IT / Engineering Lead | C90: You implement what Legal and DPO design. Focus on Granular Controls A6–A8 (consent UI/UX), C1 (security engineering), and the technical aspects of rights fulfilment, retention automation, and breach detection. Your primary sheet is Granular Controls, filtered by your applicable sections.
B91: HR / People Operations | C91: Your domain is employment data processing under Section 7(i): B5.1–B5.5 in Granular Controls (HR operations, workplace security, biometrics, employee benefits). Assess current HR systems against legitimate use requirements and biometric governance controls.
B92: Business Unit Head | C92: If your BU processes personal data independently, you are Accountable for BU-level compliance. Ensure your BU Privacy Champion and BU IT Lead are nominated and active in the RACI Matrix. Review the Express Evaluation to confirm your BU’s processing scope is captured. Track BU-specific implementation progress.
B93: Board / Executive Sponsor | C93: Your primary interface is the Compliance Dashboard. Review quarterly. Key metrics: Compliance Rate %, Implementation Rate %, Evidence Readiness %, Critical/High gaps open. Approve programme budget and timeline. Escalate when Critical gaps remain unresolved beyond target dates.
B95: 7. VERSION CONTROL & MAINTENANCE PROTOCOL
C96: Current Version | D96: v1.0 — February 2026 | Initial framework release covering DPDP Act 2023 + DPDP Rules 2025
C97: Update Triggers | D97: This framework must be updated when: (a) the Central Government issues new rules, notifications, or amendments; (b) the Data Protection Board publishes guidance, enforcement orders, or registration standards; (c) your organisation’s entity classification changes (e.g., notified as SDF); (d) new processing activities, products, or data flows are introduced; (e) annual reassessment reveals new gaps or changed risk posture.
C98: Version Log Protocol | D98: Maintain a version log (can be a separate tab or external register): Version Number | Date | Author | Change Description | Sections Affected | Approval. Distribute updated versions to all stakeholders listed in ‘Intended Users’ above. Archive previous versions for audit trail.
C99: Backup & Access Control | D99: Store this workbook in a controlled-access repository (SharePoint, GDrive with restricted permissions, or GRC platform). Maintain automated backups. Restrict edit access to DPO / Programme Office. Provide read-only access to auditors and Board members. Log access for sensitive versions.
B101: BEGIN HERE ➡ Navigate to the ‘Express Evaluation’ sheet tab and start with Section A, Question A1. Everything flows from there.

Sheet Express Evaluation
A1: DPDP COMPLIANCE FRAMEWORK — EXPRESS EVALUATION SHEET
A2: Purpose: Complete this evaluation to determine applicable compliance control domains, entity classification, and regulatory obligation scope under the DPDP Act 2023 & Rules 2025.
A3: Instructions: Answer each question using the Response column dropdown. The Applicability Result column auto-computes your applicable control domains. Complete Section A first — downstream sections depend on your entity classification.
A5: # | B5: Section | C5: Evaluation Question | D5: Response Options | E5: Your Response | F5: Applicability Result | G5: Applicable Control Domain(s) | H5: Compliance Worksheet Reference
A6: SECTION A — ENTITY CLASSIFICATION & ROLE DETERMINATION
A7: A1 | B7: Entity Classification | C7: Does your organisation determine the purpose and means of processing personal data? | D7: Yes / No | F7: =IF(E7="Yes","Data Fiduciary (DF)","Not a DF — reassess role") -> Not a DF — reassess role | G7: All DF controls (Items 1–74) | H7: Items 1–5, 12–17
A8: A2 | B8: Entity Classification | C8: Has the Central Government notified your organisation as a Significant Data Fiduciary (SDF)? | D8: Yes / No / Pending | F8: =IF(E8="Yes","SDF — enhanced obligations apply",IF(E8="Pending","Monitor notification status","Standard DF obligations")) -> Standard DF obligations | G8: SDF controls: DPO, DPIA, Audit, Algo Due-Diligence | H8: Items 49–55
A9: A3 | B9: Entity Classification | C9: Does your organisation intend to operate or currently operate as a Consent Manager? | D9: Yes / No | F9: =IF(E9="Yes","Consent Manager registration + operating obligations apply","CM controls not applicable") -> CM controls not applicable | G9: CM controls: Registration, Operations, Board Compliance | H9: Items 6–11
A10: A4 | B10: Entity Classification | C10: Does your organisation process personal data on behalf of another entity (as a Data Processor)? | D10: Yes / No | F10: =IF(E10="Yes","Processor — contractual + security obligations via DF","Not a Processor") -> Not a Processor | G10: Processor-facing controls in Items 16, 29 | H10: Items 16, 29
A11: A5 | B11: Entity Classification | C11: Is your organisation classified under Third Schedule (E-Commerce, E-Gaming, Social Media Intermediary)? | D11: Yes / No | F11: =IF(E11="Yes","Third Schedule retention + erasure rules apply","Standard retention rules apply") -> Standard retention rules apply | G11: Retention & Erasure: Items 24–28 | H11: Items 24–28
A12: SECTION B — PROCESSING SCOPE & DATA CATEGORIES
A13: B1 | B13: Processing Scope | C13: Does your organisation collect personal data directly from Data Principals (individuals)? | D13: Yes / No | F13: =IF(E13="Yes","Consent + Notice obligations apply","Assess if legitimate use applies") -> Assess if legitimate use applies | G13: Consent & Notice: A1–A2 series, Items 1–5 | H13: Items 1–5
A14: B2 | B14: Processing Scope | C14: Does your organisation process personal data based on legitimate use (Section 7) without consent? | D14: Yes / No | F14: =IF(E14="Yes","Legitimate Use controls apply — document basis per Sec 7","Consent-only processing") -> Consent-only processing | G14: Legitimate Use: B1–B6 series | H14: Item 1 (Legal Basis Register)
A15: B3 | B15: Processing Scope | C15: Does your organisation process personal data of children (under 18) or persons with disability? | D15: Yes / No | F15: =IF(E15="Yes","CRITICAL: Enhanced child/PWD data controls apply","Child data controls not required") -> Child data controls not required | G15: Children/PWD: Items 35–48, A4 series | H15: Items 35–48
A16: B4 | B16: Processing Scope | C16: Does your organisation transfer personal data outside India? | D16: Yes / No | F16: =IF(E16="Yes","Cross-border transfer controls + adequacy assessment required","Domestic processing only") -> Domestic processing only | G16: Cross-Border: Items 64–65 | H16: Items 64–65
A17: B5 | B17: Processing Scope | C17: Does your organisation process personal data for research, archiving, or statistical purposes? | D17: Yes / No | F17: =IF(E17="Yes","Second Schedule exemption framework applicable","Research exemption not relevant") -> Research exemption not relevant | G17: Research: Items 66–73 | H17: Items 66–73
A18: B6 | B18: Processing Scope | C18: Does your organisation use any Data Processors (third-party service providers processing data on your behalf)? | D18: Yes / No | F18: =IF(E18="Yes","Processor governance + contractual controls mandatory","Direct processing only") -> Direct processing only | G18: Processor Controls: Items 16, 29, B5 series | H18: Items 16, 29
A19: B7 | B19: Processing Scope | C19: Does your organisation process employee personal data (HR, payroll, biometrics, CCTV)? | D19: Yes / No | F19: =IF(E19="Yes","Employment legitimate use + biometric controls apply","Employment processing not in scope") -> Employment processing not in scope | G19: Employment: B5.1–B5.5 series, B2.9 | H19: Item 1 (Sec 7(i) basis)
A20: SECTION C — OPERATIONAL READINESS BASELINE
A21: C1 | B21: Operational Readiness | C21: Does your organisation have a documented privacy notice currently published? | D21: Yes / No / Partial | F21: =IF(E21="Yes","Verify against Rule 3/4 requirements",IF(E21="Partial","Gap remediation required","URGENT: Notice must be created")) -> URGENT: Notice must be created | G21: Notice: A1 series, Items 2, 5 | H21: Items 2, 5
A22: C2 | B22: Operational Readiness | C22: Does your organisation have a functioning consent capture and withdrawal mechanism? | D22: Yes / No / Partial | F22: =IF(E22="Yes","Validate against Sec 6 + Rule 4",IF(E22="Partial","Assess gaps in A6–A8 controls","URGENT: Consent mechanism required")) -> URGENT: Consent mechanism required | G22: Consent Ops: A2, A6–A8 series | H22: Items 3, 4
A23: C3 | B23: Operational Readiness | C23: Does your organisation have a documented breach notification process? | D23: Yes / No / Partial | F23: =IF(E23="Yes","Validate against Rule 7 timelines",IF(E23="Partial","Enhance per Items 18–23","CRITICAL: Breach playbook required")) -> CRITICAL: Breach playbook required | G23: Breach: Items 18–23, C1.1 series | H23: Items 18–23
A24: C4 | B24: Operational Readiness | C24: Does your organisation maintain a data processing inventory / Record of Processing Activities (RoPA)? | D24: Yes / No / Partial | F24: =IF(E24="Yes","Map to DPDP requirements",IF(E24="Partial","Expand to DPDP categories","FOUNDATIONAL: Build RoPA first")) -> FOUNDATIONAL: Build RoPA first | G24: Foundation for all controls | H24: All Items
A25: C5 | B25: Operational Readiness | C25: Does your organisation have a rights request handling mechanism (access, correction, erasure)? | D25: Yes / No / Partial | F25: =IF(E25="Yes","Verify against Sec 11–14 + Rule 14",IF(E25="Partial","Enhance per Items 56–62","REQUIRED: Rights mechanism needed")) -> REQUIRED: Rights mechanism needed | G25: Rights: Items 56–62 | H25: Items 56–62
A26: C6 | B26: Operational Readiness | C26: Does your organisation have security safeguards aligned to Rule 6 requirements? | D26: Yes / No / Partial | F26: =IF(E26="Yes","Validate encryption, ACL, logging, backup, monitoring",IF(E26="Partial","Gap assessment against Rule 6(a)–(g)","HIGH RISK: Security baseline required")) -> HIGH RISK: Security baseline required | G26: Security: Items 12–17, C1 series | H26: Items 12–17
A27: C7 | B27: Operational Readiness | C27: Does your organisation have a grievance redress mechanism published with SLA? | D27: Yes / No / Partial | F27: =IF(E27="Yes","Confirm ≤90-day SLA + publication",IF(E27="Partial","Publish mechanism per Rule 14(3)","REQUIRED: Grievance system needed")) -> REQUIRED: Grievance system needed | G27: Grievance: Items 61, 63 | H27: Items 61, 63
A28: C8 | B28: Operational Readiness | C28: Does your organisation have pre-existing (legacy) personal data collected before the Act? | D28: Yes / No / Unknown | F28: =IF(E28="Yes","Legacy consent migration required per Rule 3",IF(E28="Unknown","URGENT: Conduct data discovery","No legacy remediation needed")) -> No legacy remediation needed | G28: Legacy: A1.5, Item 2 | H28: Item 2
A29: SECTION D — SECTOR-SPECIFIC & BUSINESS UNIT APPLICABILITY
A30: D1 | B30: Sector Applicability | C30: Is your organisation a clinical/mental health establishment or healthcare professional? | D30: Yes / No | F30: =IF(E30="Yes","Fourth Schedule Part-A exemptions may apply for child data","Not applicable") -> Not applicable | G30: Items 36, 38–39 | H30: Items 36, 38–39
A31: D2 | B31: Sector Applicability | C31: Is your organisation an educational institution? | D31: Yes / No | F31: =IF(E31="Yes","Fourth Schedule Part-A exemption A3 applicable","Not applicable") -> Not applicable | G31: Item 40 | H31: Item 40
A32: D3 | B32: Sector Applicability | C32: Does your organisation operate a crèche, childcare centre, or child transport service? | D32: Yes / No | F32: =IF(E32="Yes","Fourth Schedule Part-A exemptions A4/A5 apply","Not applicable") -> Not applicable | G32: Items 41–42 | H32: Items 41–42
A33: D4 | B33: Sector Applicability | C33: Does your organisation process data for government scheme benefits delivery? | D33: Yes / No | F33: =IF(E33="Yes","Fourth Schedule Part-B exemption B2 applicable","Not applicable") -> Not applicable | G33: Item 43 | H33: Item 43
A34: D5 | B34: Sector Applicability | C34: Is your organisation subject to sectoral data localisation requirements (RBI, IRDAI, SEBI, CERT-In)? | D34: Yes / No / Unsure | F34: =IF(E34="Yes","Multi-layer compliance: DPDP + sectoral law",IF(E34="Unsure","Legal assessment required","DPDP-only compliance")) -> DPDP-only compliance | G34: Items 55, 65 | H34: Items 55, 65
A35: D6 | B35: Sector Applicability | C35: Does your organisation have multiple business units processing personal data independently? | D35: Yes / No | F35: =IF(E35="Yes","BU-level RACI + control ownership bifurcation required","Centralised compliance model sufficient") -> Centralised compliance model sufficient | G35: RACI Matrix — BU Layer | H35: All Items
A37: EVALUATION SUMMARY
A38: Entity Classification: | B38: =IF(E7="Yes","Data Fiduciary","") | C38: =IF(E8="Yes"," + Significant Data Fiduciary","") | D38: =IF(E9="Yes"," + Consent Manager","")
A39: Total Applicable Domains: | B39: Count responses marked 'Yes' across Sections A–D to determine scope
A40: Priority Implementation Areas: | B40: Domains where Section C responses are 'No' = highest priority
A41: Business Unit Bifurcation Required: | B41: =IF(E32="Yes","Yes — activate BU-level RACI columns","No — centralised model") -> No — centralised model

Sheet RACI Matrix
A1: DPDP COMPLIANCE FRAMEWORK — RACI RESPONSIBILITY MATRIX
A2: R = Responsible (executes) | A = Accountable (owns outcome) | C = Consulted (provides input) | I = Informed (kept updated) | BU columns enable business unit-level bifurcation of responsibilities
A3: CONTROL IDENTIFICATION | E3: CENTRAL / FUNCTIONAL OWNERSHIP (RACI) | M3: BUSINESS UNIT BIFURCATION (RACI) | P3: GOVERNANCE
A4: Control ID | B4: Domain | C4: Control / Obligation | D4: Trigger Event | E4: DPO / Privacy Office | F4: CISO / InfoSec | G4: Legal & Compliance | H4: IT / Engineering | I4: HR / People Ops | J4: Product / UX | K4: Procurement / Vendor Mgmt | L4: Business Operations | M4: BU Head (per BU) | N4: BU Privacy Champion | O4: BU IT Lead | P4: Board / Executive Sponsor | Q4: Risk Priority | R4: Implementation Phase
A5: CONSENT & NOTICE
A6: CN-01 | B6: Consent & Notice | C6: Identify Legal Basis for Processing (Consent or Legitimate Use) | D6: New/existing processing activity | E6: A | F6: C | G6: R | H6: C | I6: C | J6: C | K6: I | L6: C | M6: R | N6: C | O6: I | P6: I | Q6: P0 — Critical | R6: Phase 1
A7: CN-02 | B7: Consent & Notice | C7: Display & Serve Mandatory Standalone Notice | D7: Before requesting consent | E7: A | F7: I | G7: R | H7: R | I7: I | J7: R | K7: I | L7: C | M7: C | N7: I | O7: I | P7: I | Q7: P0 — Critical | R7: Phase 1
A8: CN-03 | B8: Consent & Notice | C8: Obtain Valid Consent (free, specific, informed, unequivocal) | D8: Consent-based processing initiation | E8: A | F8: C | G8: R | H8: R | I8: I | J8: R | K8: I | L8: I | M8: C | N8: C | O8: I | P8: I | Q8: P0 — Critical | R8: Phase 1
A9: CN-04 | B9: Consent & Notice | C9: Enable Consent Withdrawal & Stop Processing | D9: Withdrawal request received | E9: A | F9: C | G9: R | H9: R | I9: I | J9: R | K9: I | L9: I | M9: R | N9: C | O9: C | P9: I | Q9: P0 — Critical | R9: Phase 1
A10: CN-05 | B10: Consent & Notice | C10: Maintain Notice Content & Presentation Standard | D10: Creating/updating privacy notice | E10: A | F10: I | G10: R | H10: C | I10: I | J10: R | K10: I | L10: I | M10: C | N10: I | O10: I | P10: I | Q10: P1 — High | R10: Phase 1
A11: CONSENT MANAGER
A12: CM-01 | B12: Consent Manager | C12: Eligibility & Application Filing (Part A, First Schedule) | D12: Intent to operate as CM | E12: A | F12: C | G12: R | H12: R | I12: I | J12: I | K12: I | L12: C | M12: I | N12: I | O12: I | P12: A | Q12: P1 — High | R12: Phase 2
A13: CM-02 | B13: Consent Manager | C13: Board Evaluation & Decision Preparation | D13: Post application submission | E13: A | F13: C | G13: R | H13: C | I13: I | J13: I | K13: I | L13: I | M13: I | N13: I | O13: I | P13: I | Q13: P1 — High | R13: Phase 2
A14: CM-03 | B14: Consent Manager | C14: Registered CM Operating Obligations | D14: Post-registration operations | E14: A | F14: R | G14: R | H14: R | I14: I | J14: I | K14: I | L14: C | M14: I | N14: I | O14: I | P14: I | Q14: P0 — Critical | R14: Phase 2
A15: CM-04 | B15: Consent Manager | C15: Non-Adherence & Corrective Action Framework | D15: Board detects non-compliance | E15: A | F15: R | G15: R | H15: C | I15: I | J15: I | K15: I | L15: I | M15: I | N15: I | O15: I | P15: A | Q15: P1 — High | R15: Phase 2
A16: CM-05 | B16: Consent Manager | C16: Suspension / Cancellation Continuity Planning | D16: Serious breach or non-adherence | E16: A | F16: R | G16: R | H16: R | I16: I | J16: I | K16: I | L16: C | M16: I | N16: I | O16: I | P16: A | Q16: P1 — High | R16: Phase 2
A17: CM-06 | B17: Consent Manager | C17: Mandatory Information Disclosure to Board | D17: Board requests information | E17: A | F17: C | G17: R | H17: C | I17: I | J17: I | K17: I | L17: I | M17: I | N17: I | O17: I | P17: I | Q17: P1 — High | R17: Phase 2
A18: SECURITY SAFEGUARDS
A19: SS-01 | B19: Security Safeguards | C19: Implement Reasonable Security Safeguards (Rule 6 baseline) | D19: Processing/storing/transmitting PD | E19: C | F19: A | G19: C | H19: R | I19: I | J19: I | K19: C | L19: I | M19: C | N19: I | O19: R | P19: I | Q19: P0 — Critical | R19: Phase 1
A20: SS-02 | B20: Security Safeguards | C20: Access Control & Monitoring (Rule 6(b)(c)) | D20: Data access/modification/export | E20: C | F20: A | G20: I | H20: R | I20: C | J20: I | K20: I | L20: I | M20: C | N20: I | O20: R | P20: I | Q20: P0 — Critical | R20: Phase 1
A21: SS-03 | B21: Security Safeguards | C21: Data Availability, Integrity & Backup (Rule 6(d)) | D21: CIA risk to personal data | E21: C | F21: A | G21: I | H21: R | I21: I | J21: I | K21: I | L21: I | M21: I | N21: I | O21: R | P21: I | Q21: P0 — Critical | R21: Phase 1
A22: SS-04 | B22: Security Safeguards | C22: Log Retention & Breach Detection (Rule 6(e)) | D22: Breach/unauthorised access occurs or may occur | E22: C | F22: A | G22: C | H22: R | I22: I | J22: I | K22: I | L22: I | M22: C | N22: I | O22: R | P22: I | Q22: P0 — Critical | R22: Phase 1
A23: SS-05 | B23: Security Safeguards | C23: Security Obligations in Processor Contracts (Rule 6(f)) | D23: Using any Data Processor | E23: C | F23: A | G23: R | H23: C | I23: I | J23: I | K23: R | L23: I | M23: C | N23: I | O23: I | P23: I | Q23: P0 — Critical | R23: Phase 1
A24: SS-06 | B24: Security Safeguards | C24: Technical & Organisational Measures — Ongoing (Rule 6(g)) | D24: Continuous operations | E24: C | F24: A | G24: C | H24: R | I24: I | J24: I | K24: I | L24: I | M24: C | N24: I | O24: R | P24: I | Q24: P1 — High | R24: Phase 2
A25: BREACH NOTIFICATION
A26: BN-01 | B26: Breach Notification | C26: Breach Awareness & Activation (incl. Processor breach) | D26: Breach awareness | E26: R | F26: A | G26: R | H26: R | I26: I | J26: I | K26: C | L26: I | M26: R | N26: C | O26: R | P26: I | Q26: P0 — Critical | R26: Phase 1
A27: BN-02 | B27: Breach Notification | C27: Internal Verification & Scope Assessment | D27: Breach confirmed involving PD | E27: R | F27: A | G27: R | H27: R | I27: I | J27: I | K27: I | L27: I | M27: C | N27: C | O27: C | P27: I | Q27: P0 — Critical | R27: Phase 1
A28: BN-03 | B28: Breach Notification | C28: Notification to Affected Data Principals (Rule 7(1)) | D28: Required info available without delay | E28: R | F28: R | G28: A | H28: R | I28: I | J28: R | K28: I | L28: I | M28: R | N28: I | O28: I | P28: I | Q28: P0 — Critical | R28: Phase 1
A29: BN-04 | B29: Breach Notification | C29: First Intimation to Board (Rule 7(2)(a)) | D29: Immediately after breach-awareness | E29: R | F29: R | G29: A | H29: C | I29: I | J29: I | K29: I | L29: I | M29: C | N29: I | O29: I | P29: I | Q29: P0 — Critical | R29: Phase 1
A30: BN-05 | B30: Breach Notification | C30: Detailed Follow-Up Submission to Board (Rule 7(2)(b)) | D30: Within 72 hours | E30: R | F30: R | G30: A | H30: R | I30: I | J30: I | K30: I | L30: I | M30: C | N30: C | O30: C | P30: I | Q30: P0 — Critical | R30: Phase 1
A31: BN-06 | B31: Breach Notification | C31: Evidence Preservation & Retention | D31: Throughout breach handling | E31: R | F31: A | G31: R | H31: R | I31: I | J31: I | K31: I | L31: I | M31: C | N31: I | O31: R | P31: I | Q31: P0 — Critical | R31: Phase 1
A32: BN-07 | B32: Breach Notification | C32: Breach Notification During Retention / Pre-Erasure Period | D32: Breach during retention window | E32: R | F32: A | G32: R | H32: R | I32: I | J32: I | K32: I | L32: I | M32: C | N32: I | O32: R | P32: I | Q32: P1 — High | R32: Phase 2
A33: RETENTION & ERASURE
A34: RE-01 | B34: Retention & Erasure | C34: Applicability Confirmation (Third Schedule Class + Purpose) | D34: Org qualifies under Third Schedule | E34: A | F34: I | G34: R | H34: C | I34: I | J34: C | K34: I | L34: C | M34: R | N34: C | O34: I | P34: I | Q34: P1 — High | R34: Phase 1
A35: RE-02 | B35: Retention & Erasure | C35: Trigger for Purpose-Based Erasure | D35: No DP engagement for purpose | E35: A | F35: C | G35: R | H35: R | I35: I | J35: R | K35: I | L35: C | M35: R | N35: C | O35: R | P35: I | Q35: P1 — High | R35: Phase 2
A36: RE-03 | B36: Retention & Erasure | C36: Mandatory 48-Hour Pre-Erasure Notice | D36: 48hrs before scheduled erasure | E36: A | F36: I | G36: C | H36: R | I36: I | J36: R | K36: I | L36: I | M36: C | N36: I | O36: R | P36: I | Q36: P1 — High | R36: Phase 2
A37: RE-04 | B37: Retention & Erasure | C37: Minimum One-Year Statutory Retention (Rule 8(3)) | D37: Any PD processing | E37: A | F37: R | G37: R | H37: R | I37: C | J37: I | K37: C | L37: I | M37: C | N37: C | O37: R | P37: I | Q37: P0 — Critical | R37: Phase 1
A38: RE-05 | B38: Retention & Erasure | C38: Final Erasure Execution (Rule 8(1)+8(2)+8(3)) | D38: All erasure pre-conditions met | E38: A | F38: R | G38: C | H38: R | I38: I | J38: I | K38: C | L38: I | M38: C | N38: I | O38: R | P38: I | Q38: P1 — High | R38: Phase 2
A39: RE-06 | B39: Retention & Erasure | C39: Security Safeguard Overlay over Processors | D39: Throughout lifecycle incl. backup | E39: C | F39: A | G39: C | H39: R | I39: I | J39: I | K39: R | L39: I | M39: C | N39: I | O39: R | P39: I | Q39: P1 — High | R39: Phase 2
A40: CHILDREN & PWD DATA
A41: CD-01 | B41: Children & PWD Data | C41: Data Protection & Security Safeguards for Child Data | D41: Collection through deletion | E41: A | F41: R | G41: R | H41: R | I41: C | J41: R | K41: I | L41: I | M41: R | N41: C | O41: R | P41: I | Q41: P0 — Critical | R41: Phase 1
A42: CD-02 | B42: Children & PWD Data | C42: Fourth Schedule Part-A Class Exemption Assessment | D42: DF falls under Part-A class | E42: A | F42: I | G42: R | H42: I | I42: C | J42: C | K42: I | L42: C | M42: R | N42: I | O42: I | P42: I | Q42: P1 — High | R42: Phase 2
A43: CD-03 | B43: Children & PWD Data | C43: Fourth Schedule Part-B Purpose Exemption Assessment | D43: Processing under Part-B purpose | E43: A | F43: I | G43: R | H43: C | I43: I | J43: C | K43: I | L43: C | M43: R | N43: I | O43: I | P43: I | Q43: P1 — High | R43: Phase 2
A44: CD-04 | B44: Children & PWD Data | C44: Age Confirmation Mechanism (Rule 10) | D44: Need to confirm user is not child | E44: A | F44: R | G44: R | H44: R | I44: I | J44: R | K44: I | L44: I | M44: R | N44: C | O44: R | P44: I | Q44: P0 — Critical | R44: Phase 1
A45: SDF OBLIGATIONS
A46: SDF-01 | B46: SDF Obligations | C46: Appointment of Data Protection Officer (DPO) | D46: Upon SDF declaration | E46: R | F46: C | G46: R | H46: I | I46: C | J46: I | K46: I | L46: I | M46: I | N46: I | O46: I | P46: A | Q46: P0 — Critical | R46: Phase 1
A47: SDF-02 | B47: SDF Obligations | C47: Appointment of Independent Data Auditor | D47: Upon becoming SDF | E47: A | F47: C | G47: R | H47: I | I47: I | J47: I | K47: R | L47: I | M47: I | N47: I | O47: I | P47: I | Q47: P1 — High | R47: Phase 2
A48: SDF-03 | B48: SDF Obligations | C48: Mandatory Annual DPIA (Rule 13(1)) | D48: Every 12-month cycle | E48: A | F48: R | G48: R | H48: C | I48: C | J48: C | K48: I | L48: C | M48: C | N48: C | O48: I | P48: I | Q48: P0 — Critical | R48: Phase 2
A49: SDF-04 | B49: SDF Obligations | C49: Mandatory Annual Audit (Rule 13(1)) | D49: Every 12-month cycle | E49: A | F49: R | G49: R | H49: C | I49: C | J49: I | K49: C | L49: C | M49: C | N49: C | O49: I | P49: I | Q49: P0 — Critical | R49: Phase 2
A50: SDF-05 | B50: SDF Obligations | C50: Regulatory Reporting of DPIA + Audit (Rule 13(2)) | D50: After each cycle completion | E50: A | F50: C | G50: R | H50: I | I50: I | J50: I | K50: I | L50: I | M50: I | N50: I | O50: I | P50: I | Q50: P1 — High | R50: Phase 2
A51: SDF-06 | B51: SDF Obligations | C51: Technical Due-Diligence for Algorithmic Risks (Rule 13(3)) | D51: Using hosting/processing systems | E51: C | F51: A | G51: C | H51: R | I51: I | J51: R | K51: C | L51: I | M51: C | N51: I | O51: R | P51: I | Q51: P1 — High | R51: Phase 2
A52: SDF-07 | B52: SDF Obligations | C52: Data + Traffic Flow Localisation (Rule 13(4)–(5)) | D52: When CG specifies categories | E52: A | F52: R | G52: R | H52: R | I52: I | J52: I | K52: I | L52: I | M52: C | N52: I | O52: R | P52: I | Q52: P1 — High | R52: Phase 3
A53: DATA PRINCIPAL RIGHTS
A54: DPR-01 | B54: Data Principal Rights | C54: Rights Request Enablement & Publishing (Rule 14(1)) | D54: DF processes PD + must enable requests | E54: A | F54: I | G54: R | H54: R | I54: I | J54: R | K54: I | L54: I | M54: C | N54: C | O54: I | P54: I | Q54: P0 — Critical | R54: Phase 1
A55: DPR-02 | B55: Data Principal Rights | C55: Rights Request Submission Path (Rule 14(2)) | D55: DP exercises any right | E55: A | F55: I | G55: C | H55: R | I55: I | J55: R | K55: I | L55: I | M55: R | N55: C | O55: C | P55: I | Q55: P1 — High | R55: Phase 2
A56: DPR-03 | B56: Data Principal Rights | C56: Rights-Enabling Identifier Requirements (Rule 14(1)(b)) | D56: Identity verification before action | E56: A | F56: R | G56: R | H56: R | I56: I | J56: I | K56: I | L56: I | M56: C | N56: C | O56: C | P56: I | Q56: P1 — High | R56: Phase 2
A57: DPR-04 | B57: Data Principal Rights | C57: Right to Access — Response Content (Sec 11) | D57: Verified access request | E57: A | F57: I | G57: R | H57: R | I57: I | J57: I | K57: I | L57: I | M57: R | N57: C | O57: C | P57: I | Q57: P1 — High | R57: Phase 2
A58: DPR-05 | B58: Data Principal Rights | C58: Rights to Correction, Completion, Updating & Erasure (Sec 12) | D58: DP submits correction/erasure request | E58: A | F58: C | G58: R | H58: R | I58: C | J58: I | K58: I | L58: I | M58: R | N58: C | O58: R | P58: I | Q58: P1 — High | R58: Phase 2
A59: DPR-06 | B59: Data Principal Rights | C59: Grievance Redress System (Sec 13, Rule 14(3)) | D59: DP files grievance | E59: A | F59: I | G59: R | H59: R | I59: I | J59: I | K59: I | L59: C | M59: R | N59: C | O59: I | P59: I | Q59: P0 — Critical | R59: Phase 1
A60: DPR-07 | B60: Data Principal Rights | C60: Nomination Rights (Sec 14, Rule 14(4)) | D60: DP opts to nominate | E60: A | F60: I | G60: R | H60: R | I60: I | J60: R | K60: I | L60: I | M60: C | N60: I | O60: I | P60: I | Q60: P2 — Medium | R60: Phase 3
A61: DPR-08 | B61: Data Principal Rights | C61: Publishing Time-Bound Grievance Response Capability | D61: DF/CM manages grievances | E61: A | F61: I | G61: R | H61: C | I61: I | J61: R | K61: I | L61: I | M61: C | N61: I | O61: I | P61: I | Q61: P1 — High | R61: Phase 2
A62: CROSS-BORDER TRANSFER
A63: CBT-01 | B63: Cross-Border Transfer | C63: Cross-Border Personal Data Transfer Enablement (Rule 15) | D63: Intent to transfer PD outside India | E63: A | F63: R | G63: R | H63: R | I63: I | J63: I | K63: C | L63: I | M63: R | N63: C | O63: R | P63: I | Q63: P1 — High | R63: Phase 2
A64: CBT-02 | B64: Cross-Border Transfer | C64: Compliance With Higher Restriction Laws (Sec 16(2)) | D64: Sectoral law imposes stricter rules | E64: A | F64: R | G64: R | H64: R | I64: I | J64: I | K64: C | L64: I | M64: R | N64: C | O64: R | P64: I | Q64: P1 — High | R64: Phase 2
A65: RESEARCH & ARCHIVING
A66: RA-01 | B66: Research & Archiving | C66: Eligibility for Research/Archiving/Statistical Exemption | D66: DF plans exempt processing | E66: A | F66: C | G66: R | H66: C | I66: I | J66: I | K66: I | L66: C | M66: C | N66: I | O66: I | P66: I | Q66: P2 — Medium | R66: Phase 3
A67: RA-02 | B67: Research & Archiving | C67: Lawfulness + Minimisation + Accuracy + Retention + Security | D67: Research processing lifecycle | E67: A | F67: R | G67: R | H67: R | I67: I | J67: I | K67: I | L67: C | M67: C | N67: C | O67: C | P67: I | Q67: P2 — Medium | R67: Phase 3
A68: RA-03 | B68: Research & Archiving | C68: Accountability Obligation (Sec 17(2)(b)) | D68: DF determines research purpose | E68: A | F68: C | G68: R | H68: C | I68: I | J68: I | K68: I | L68: C | M68: C | N68: I | O68: I | P68: I | Q68: P2 — Medium | R68: Phase 3
A69: GOVT. INFORMATION REQUESTS
A70: GR-01 | B70: Govt. Information Requests | C70: Furnishing Information to Central Government (Sec 36, Rule 23) | D70: Govt issues information requisition | E70: A | F70: R | G70: R | H70: R | I70: I | J70: I | K70: I | L70: I | M70: C | N70: I | O70: I | P70: A | Q70: P0 — Critical | R70: Phase 1
A71: CONTACT & PUBLICATION
A72: CP-01 | B72: Contact & Publication | C72: Contact Information Publication (Sec 8(9), Rule 9) | D72: DF processes PD + may receive queries | E72: A | F72: I | G72: R | H72: R | I72: I | J72: R | K72: I | L72: I | M72: C | N72: I | O72: I | P72: I | Q72: P1 — High | R72: Phase 1
A73: CP-02 | B73: Contact & Publication | C73: DPO Contact Requirement Applicability (Sec 10(2), Rule 9) | D73: SDF determination | E73: A | F73: I | G73: R | H73: C | I73: C | J73: I | K73: I | L73: I | M73: I | N73: I | O73: I | P73: I | Q73: P1 — High | R73: Phase 1

Sheet Assessment + Implementation
A1: DPDP COMPLIANCE FRAMEWORK — DUAL ASSESSMENT & IMPLEMENTATION TRACKER
A2: Assessment Area: Current-state evaluation of control maturity | Implementation Area: Forward-looking action tracking toward compliance target state
A3: CONTROL IDENTIFICATION | K3: ASSESSMENT AREA (Current State) | P3: IMPLEMENTATION AREA (Target State) | V3: GOVERNANCE & EVIDENCE
A4: Sr. No. | B4: Control ID | C4: Category | D4: Priority | E4: DPDP Section | F4: Max Penalty | G4: Reference | H4: Role / Responsibility | I4: Compliance Header | J4: Compliance Measures | K4: Assessment Status | L4: Maturity Level | M4: Gap Identified | N4: Gap Description | O4: Risk Rating | P4: Impl. Status | Q4: Accountable Owner | R4: Target Date | S4: Action Plan / Remediation | T4: Budget Est. (INR) | U4: % Complete | V4: Evidence Status | W4: Evidence Artefact / Location | X4: Last Review Date | Y4: Reviewer Comments
A5: 1 | B5: CN-01 | C5: Consent & Notice | D5: Critical | E5: Sec. 4, 5, 6, Rule 3 | F5: ₹50 Cr | G5: Section 4, 5, 6, read with Rule 3 | H5: Data Fiduciary | I5: Identify Legal Basis for Processing (Consent or Legitimate Use) | J5: • Maintain Processing + Legal Basis Register • Classify each processing into Consent or Legitimate Use before execution • Disallow bundled, conditional, forced, misleading basis selection • Flag and approve purpose change via governance workflow | K5: Partially Compliant | L5: 2 | M5: Yes | N5: Legal basis register exists for 60% of processing activities. New product lines (launched Q4 2025) not yet mapped. No governance workflow for purpose changes. | O5: High | P5: In Progress | Q5: Head of Legal | R5: 46203 | S5: Complete processing inventory for new product lines. Deploy purpose-change approval workflow in GRC tool. Train product teams on legal basis classification. | T5: 1200000 | U5: 0.45 | V5: Collected | W5: Legal Basis Register v2.3 — SharePoint/Privacy/LegalBasis/ | X5: 46068 | Y5: Register needs expansion to cover 3 new product lines. Workflow tool RFP in progress.
A6: 2 | B6: CN-02 | C6: Consent & Notice | D6: High | E6: Sec. 4, 5, 6, Rule 3 | F6: ₹50 Cr | G6: Section 4, 5, 6, read with Rule 3 | H6: Data Fiduciary | I6: Display & Serve Mandatory Notice (Standalone Notice) | J6: • Use separate notice (not merged with T&Cs/marketing) • Capture timestamp + notice version displayed • Provide direct links to rights, grievance & withdrawal page • Ensure notice remains accessible after consent
A7: 3 | B7: CN-03 | C7: Consent & Notice | D7: Critical | E7: Sec. 4, 5, 6, Rule 3 | F7: ₹50 Cr | G7: Section 4, 5, 6, read with Rule 3 | H7: Data Fiduciary | I7: Obtain Valid Consent | J7: • Use explicit action (tick-box, signature, OTP, click-accept) • Store consent evidence log: DP ID, timestamp, notice version, purpose, method • Block processing until consent proof exists • Prohibit reuse for new purposes unless re-consented | K7: Non-Compliant | L7: 1 | M7: Yes | N7: Consent captured via pre-ticked checkboxes on legacy web forms. No consent evidence log. Consent reused across purposes without re-consent. | O7: Critical | P7: Planning | Q7: Head of Product | R7: 46265 | S7: Replace pre-ticked checkboxes with explicit opt-in. Deploy consent SDK with granular purpose selection. Build consent evidence log (DP ID, timestamp, version, purpose, method). | T7: 3500000 | U7: 0.1 | V7: Not Collected | X7: 46068 | Y7: Legacy forms require complete rebuild. SDK vendor shortlisted.
A8: 4 | B8: CN-04 | C8: Consent & Notice | D8: High | E8: Sec. 4, 5, 6, Rule 3 | F8: ₹50 Cr | G8: Section 4, 5, 6, read with Rule 3 | H8: Data Fiduciary | I8: Enable Consent Withdrawal & Stop Processing After Withdrawal | J8: • Provide easy withdrawal method equal to effort of giving consent • Trigger automated blocking of further processing • Notify processors + internal systems to disable access/processing • Maintain withdrawal log: timestamp, scope, impacted systems
A9: 5 | B9: CN-05 | C9: Consent & Notice | D9: High | E9: Sec. 4, 5, 6, Rule 3 | F9: ₹50 Cr | G9: Section 4, 5, 6, read with Rule 3 | H9: Data Fiduciary | I9: Maintain Notice Content & Presentation Standard | J9: • Maintain central notice template + version control repository • Conduct legal + UX clarity review before publishing • Publish separately from marketing, commercial terms, or disclaimers • Retain historical versions + publication logs
A10: 6 | B10: CM-01 | C10: Consent Manager | D10: Medium | E10: Sec. 6(9), Rule 4 | F10: ₹50 Cr | G10: Section 6(9) read with Rule 4 | H10: Consent Managers | I10: Eligibility & Application Filing | J10: • Prepare evidence for all Part A criteria (technical, security, operational, financial, governance) • Collect documentary proof as per Board-published checklist • Prepare system architecture, SOPs and support model
A11: 7 | B11: CM-02 | C11: Consent Manager | D11: Medium | E11: Sec. 6(9), Rule 4 | F11: ₹50 Cr | G11: Section 6(9) read with Rule 4 | H11: Consent Managers | I11: Board Evaluation & Decision | J11: • Maintain verifiable compliance documentation • Ensure alignment between documentation and actual operations • Keep audit logs ready for demonstration
A12: 8 | B12: CM-03 | C12: Consent Manager | D12: High | E12: Sec. 6(9), Rule 4 | F12: ₹50 Cr | G12: Section 6(9) read with Rule 4 | H12: Consent Managers | I12: Registered Consent Manager Operating Obligations | J12: • Implement secure, transparent consent lifecycle handling • Maintain neutrality and non-manipulative flow • Maintain audit-ready operational logs and uptime records
A13: 9 | B13: CM-04 | C13: Consent Manager | D13: Medium | E13: Sec. 6(9), Rule 4 | F13: ₹50 Cr | G13: Section 6(9) read with Rule 4 | H13: Consent Managers | I13: Non-Adherence & Corrective Action | J13: • Operate continuous compliance assurance framework (CCAF) • Perform quarterly internal control audits and evidence-based testing • Implement tracked remediation plan with accountable owners and closure proof • Maintain regulatory response file with artefacts, logs, and timeline trail
A14: 10 | B14: CM-05 | C14: Consent Manager | D14: Low | E14: Sec. 6(9), Rule 4 | F14: ₹50 Cr | G14: Section 6(9) read with Rule 4 | H14: Consent Managers | I14: Suspension or Cancellation Power | J14: • Maintain live Business Continuity & Service Continuity Framework • Establish regulated handover, exit and portability mechanism for data and consent records • Maintain immutable traceability logs for every consent lifecycle event • Define shutdown, escrow, archival & return-of-data playbooks • Maintain contractual exit clauses with processors and technical partners
A15: 11 | B15: CM-06 | C15: Consent Manager | D15: Low | E15: Sec. 6(9), Rule 4 | F15: ₹50 Cr | G15: Section 6(9) read with Rule 4 | H15: Consent Managers | I15: Mandatory Information Disclosure to Board | J15: • Maintain central evidence and document repository • Maintain version-controlled policies, logs, audit records, and incident reports • Adopt formal Board-response SOP with internal SLAs • Maintain traceable response documentation & authorised sign-off
A16: 12 | B16: SS-01 | C16: Security Safeguards | D16: Critical | E16: Sec. 8(5), Rule 6 | F16: ₹250 Cr | G16: Section 8(5) read with Rule 6 | H16: Data Fiduciary | I16: Implement Reasonable Security Safeguards | J16: • Maintain real-time data inventory & data-flow register including processors • Encrypt/mask/tokenise personal data at rest & in transit • Enforce role-based access, MFA, least-privilege & Just-in-Time access • Enable continuous monitoring, log retention & breach alerting • Implement backup & continuity aligned to criticality & restoration objectives • Include enforceable security clauses in all processor contracts • Maintain approved security policy, SOPs, and evidence repositories | K16: Partially Compliant | L16: 2 | M16: Yes | N16: Encryption at rest implemented (AES-256). MFA enforced for privileged access. Gaps: no centralised log retention policy, backup restoration testing not quarterly, processor security clauses incomplete in 4 of 12 contracts. | O16: Critical | P16: In Progress | Q16: CISO | R16: 46234 | S16: Implement centralised SIEM with 1-year log retention. Schedule quarterly backup restoration drills. Amend 4 processor contracts to include Rule 6 security clauses. | T16: 8500000 | U16: 0.55 | V16: Collected | W16: SIEM Config Docs — Confluence/Security/SIEM; Encryption Audit Report Feb 2026 | X16: 46073 | Y16: SIEM deployment 60% complete. Processor contract amendments drafted, pending legal review.
A17: 13 | B17: SS-02 | C17: Security Safeguards | D17: High | E17: Rule 6(b), 6(c) | F17: ₹250 Cr | G17: Rule 6(b), 6(c) | H17: Data Fiduciary | I17: Access Control & Monitoring | J17: • Enforce role-based, context-based, and least-privilege access assignments • Enforce MFA & strong authentication for privileged and remote access • Maintain logged workflow for access requests, approvals, revocations, & periodic certification • Implement real-time monitoring & anomaly alerting • Conduct quarterly access control & log review with documented outcomes
A18: 14 | B18: SS-03 | C18: Security Safeguards | D18: High | E18: Rule 6(d) | F18: ₹250 Cr | G18: Rule 6(d) | H18: Data Fiduciary | I18: Data Availability, Integrity & Backup Measures | J18: • Maintain encrypted and integrity-verified backups including both online and offline copies based on data criticality • Store critical data copies in a tamper-resistant, offline, or isolated (air-gapped) environment • Maintain a documented Business Continuity Plan and Disaster Recovery Plan (BCP/DRP) with clearly defined restoration timelines and recovery expectations • Conduct quarterly data restoration, failover, and disaster simulation testing with evidence • Use checksum or cryptographic ha
A19: 15 | B19: SS-04 | C19: Security Safeguards | D19: High | E19: Rule 6(e) | F19: ₹250 Cr | G19: Rule 6(e) | H19: Data Fiduciary | I19: Log Retention & Breach Detection Visibility | J19: • Maintain a centralised, tamper-resistant logging system covering user activity, system events, and data access • Protect logs using write-once or restricted-permission storage controls so they cannot be altered or deleted • Enable real-time alerting and correlation rules to identify abnormal behaviour • Maintain an incident investigation and evidence-preservation workflow with time-stamped triage records • Retain incident-related logs separately until closure of investigation, legal hold, or r
A20: 16 | B20: SS-05 | C20: Security Safeguards | D20: High | E20: Rule 6(f) | F20: ₹250 Cr | G20: Rule 6(f) | H20: Data Fiduciary | I20: Security Obligations in Processor Contracts | J20: • Draft and enforce mandatory data protection and security clauses including: encryption, secure access management, logging, monitoring, incident reporting timelines, data return/deletion terms, subcontracting restrictions, and audit/cooperation rights • Perform documented due-diligence and periodic risk assessments on every Data Processor • Maintain evidence repository including contract versions, evaluation records, risk scores, and remediation reports
A21: 17 | B21: SS-06 | C21: Security Safeguards | D21: Medium | E21: Rule 6(g) | F21: ₹250 Cr | G21: Rule 6(g) | H21: Data Fiduciary | I21: Technical & Organisational Measures (Ongoing) | J21: • Operate a continuous compliance and threat monitoring function • Conduct scheduled security assessments, penetration testing, and configuration reviews • Maintain secure software development lifecycle (SSDLC) controls for product and feature releases • Ensure mandatory periodic security and privacy training for all relevant personnel • Record evidence-based audit trails of testing, remediation and control maturity improvements
A22: 18 | B22: BN-01 | C22: Breach Notification | D22: Critical | E22: Sec. 8(6), Rule 7(1), 7(2) | F22: ₹200 Cr | G22: Section 8(6) read with Rule 7(1) & Rule 7(2) | H22: Data Fiduciary | I22: Breach Awareness & Activation (Including Processor-Caused Breach) | J22: • Contractually mandate immediate breach reporting SLA from Processor to Data Fiduciary (example: within two hours of detection) • Integrate Processor incident escalation into incident response playbooks and information security management procedures • Establish single, logged intake channel for all Processor breach submissions • Maintain forensic-grade evidence and chain-of-custody records, even if evidence originates from Processor-owned infrastructure | K22: Non-Compliant | L22: 0 | M22: Yes | N22: No documented breach response playbook. Processor contracts lack breach reporting SLAs. No forensic evidence chain-of-custody protocol. Ad-hoc incident handling only. | O22: Critical | P22: Planning | Q22: CISO | R22: 46295 | S22: Develop breach response playbook aligned to Rule 7. Mandate 2-hour processor breach reporting SLA in all contracts. Establish forensic evidence preservation protocol. Conduct tabletop simulation. | T22: 2000000 | U22: 0.05 | V22: Not Collected | X22: 46068 | Y22: Critical gap. Board briefed. Playbook development starting March 2026.
A23: 19 | B23: BN-02 | C23: Breach Notification | D23: High | E23: Sec. 8(6), Rule 7(1)(a-e), 7(2)(a) | F23: ₹200 Cr | G23: Section 8(6) read with Rule 7(1)(a)–(e) & Rule 7(2)(a) | H23: Data Fiduciary | I23: Initial Internal Verification & Scope Assessment | J23: • Activate documented breach assessment runbook • Classify impacted data type, identifiability, volume, and potential harm indicators • Validate and evidence Processor-side logs, configurations, and timestamps • Record two timestamps separately: (i) time of breach occurrence/detection, (ii) time of awareness by Fiduciary • Maintain authoritative registry of user communication channels and delivery preferences for notification execution
A24: 20 | B24: BN-03 | C24: Breach Notification | D24: High | E24: Sec. 8(6), Rule 7(1)(a-e) | F24: ₹200 Cr | G24: Section 8(6) read with Rule 7(1)(a)–€ | H24: Data Fiduciary | I24: Notification to Affected Data Principals | J24: • Maintain pre-approved notification templates aligned to each clause of Rule 7(1)(a)–(e) • Use verified and active communication channel such as registered email, SMS, in-app notification, or account dashboard • Retain proof of delivery, read-status where feasible, and escalation log for unreachable individuals
A25: 21 | B25: BN-04 | C25: Breach Notification | D25: High | E25: Sec. 8(6), Rule 7(2)(a) | F25: ₹200 Cr | G25: Section 8(6) read with Rule 7(2)(a) | H25: Data Fiduciary | I25: First Intimation to the Board | J25: • Use pre-approved regulatory reporting template • Ensure authorised sign-off (not below designated senior compliance / privacy officer) • Capture exact timestamp of awareness and submission • Store acknowledgement and follow-up references • Clearly disclose whether the breach originated from Processor environment
A26: 22 | B26: BN-05 | C26: Breach Notification | D26: High | E26: Sec. 8(6), Rule 7(2)(b) | F26: ₹200 Cr | G26: Section 8(6) read with Rule 7(2)(b)(i)–(vi) | H26: Data Fiduciary | I26: Detailed Follow-Up Submission to Board | J26: • Obtain complete event timeline, technical logs, forensics evidence and incident artefacts (including from Processor) • Conduct structured Root-Cause-Analysis with named accountable owners • Submit corrective action plan with milestones and validation criteria • Attach evidence repository including Data Principal notification proof, Processor breach documentation and chain-of-custody trail
A27: 23 | B27: BN-06 | C27: Breach Notification | D27: High | E27: Sec. 8(6), Rule 7 | F27: ₹200 Cr | G27: Section 8(6) read with Rule 7(1) & Rule 7(2) | H27: Data Fiduciary | I27: Evidence Preservation & Retention | J27: • Maintain tamper-resistant preservation of all incident artefacts including logs, alerts, communication records, forensics outputs, screenshots, tickets, emails and investigation minutes • Require Processor to retain and supply logs and artefacts in original, unaltered form • Maintain separate, access-controlled incident evidence repository with immutability controls for regulatory and audit reference
A28: 24 | B28: RE-01 | C28: Retention & Erasure | D28: Medium | E28: Rule 8(1) | F28: ₹50 Cr | G28: Rule 8(1) | H28: Data Fiduciary (E-Commerce, E-Gaming & Social Media Intermediary) | I28: Applicability Confirmation (Class + Purpose) | J28: • Conduct and document classification assessment with evidence • Maintain purpose-to-class mapping and review on any change • Track user-population / business-model changes that may alter classification • Maintain periodic re-validation record for all active processing purposes
A29: 25 | B29: RE-02 | C29: Retention & Erasure | D29: Medium | E29: Rule 8(1) | F29: ₹50 Cr | G29: Rule 8(1) | H29: Data Fiduciary (E-Commerce, E-Gaming & Social Media Intermediary) | I29: Trigger for Purpose-Based Erasure | J29: • Maintain objectively recorded last-interaction timestamp • Configure purpose-specific retention timers • Prevent non-DP-initiated auto-renewal events • Ensures confirmation based Deletion/Account Removals.
A30: 26 | B30: RE-03 | C30: Retention & Erasure | D30: Medium | E30: Rule 8(2) | F30: ₹50 Cr | G30: Rule 8(2) | H30: Data Fiduciary (E-Commerce, E-Gaming & Social Media Intermediary) | I30: Mandatory 48-Hour Pre-Erasure Notice | J30: • Maintain verifiable, system-generated last-interaction timestamp tied to the specific purpose • Configure purpose-specific, non-extendable retention timers mapped to Third Schedule requirements • Disable auto-renewal, auto-login, passive reactivation or inferred-activity extensions that would silently prolong retention • Implement confirmed-erasure workflow including account-level and dataset-level deletion acknowledgements
A31: 27 | B31: RE-04 | C31: Retention & Erasure | D31: High | E31: Sec. 8(5), Rule 8(3) | F31: ₹50 Cr | G31: Section 8(5) read with Rule 8(3) | H31: Data Fiduciary | I31: Rule 8(3) – Minimum One-Year Statutory Retention | J31: • Maintain a central retention register capturing data category, source, purpose, legal retention basis, retention start date and minimum mandated end-date • Update processor contracts and SoWs to include minimum 1-year retention, controlled deletion timeline and evidentiary delivery obligations • Ensure archival, DR, and backup systems enforce the same retention controls • Disallow deletion requests unless supported by Seventh Schedule justification and post-minimum-period eligibility | K31: Compliant | L31: 3 | M31: No | O31: Low | P31: Implemented | Q31: Head of IT | R31: 46053 | S31: Central retention register deployed. Minimum 1-year retention enforced across all systems. Processor contracts updated with retention clauses. | T31: 500000 | U31: 1 | V31: Validated | W31: Retention Register v1.0 — GRC Platform; Processor Contract Addendums — Legal/Contracts/ | X31: 46053 | Y31: Fully implemented and validated by internal audit Jan 2026.
A32: 28 | B32: RE-05 | C32: Retention & Erasure | D32: Medium | E32: Sec. 8(5), 12(3), Rule 8 | F32: ₹50 Cr | G32: Section 8(5) read with Section 12(3) read with Rule 8(1), 8(2), 8(3) | H32: Data Fiduciary | I32: Rule 8(1) + 8(2) + 8(3) – Final Erasure Execution | J32: • Use a controlled erasure workflow (no masking, anonymisation, or reversible soft-delete counted as erasure) • Capture tamper-proof audit evidence: request ID, authoriser, timestamp, data scope, and system-level confirmation • Obtain deletion proof from processors and sub-processors including backup repositories • Conduct erasure reconciliation checks to confirm no residual artefacts remain in logs, caches, analytics, shadow storages.
A33: 29 | B33: RE-06 | C33: Security Safeguards | D33: High | E33: Sec. 8(5), Rule 6 | F33: ₹250 Cr | G33: Section 8(5) read with Rule 6 | H33: Data Fiduciary | I33: Security Safeguard Overlay over Processors | J33: • Apply full security safeguards consistently across live, mirrored, archived, dormant, backup, and pre-erasure environments • Conduct periodic privileged access review, log audit and processor security performance validation • Enforce ongoing contractual compliance including evidence-based controls testing for all processors and sub-processors
A34: 30 | B34: BN-07 | C34: Breach Notification | D34: Medium | E34: Sec. 8(5), Rule 7 | F34: ₹200 Cr | G34: Section 8(5) read with Rule 7 | H34: Data Fiduciary | I34: Breach Notification During Retention / Inactivity / Pre-Erasure Period | J34: • Extend breach-response SOP and incident classification matrix to include archived, inactive, dormant, cold-storage and backup environments • Mandate contractual breach reporting SLA for processors and sub-processors aligned to fiduciary timelines • Maintain legally defensible, searchable, and tamper-proof logs for the full duration of the retention period
A35: 31 | B35: CP-01 | C35: Contact & Publication | D35: Medium | E35: Sec. 8(9), Rule 9 | F35: ₹50 Cr | G35: Section 8(9) read with Rule 9 | H35: Data Fiduciary | I35: Contact Information Publication Obligation | J35: • Publish a single official and monitored contact point (not generic marketing, customer support, ticket-bot or promotional addresses) • Place contact information in mandatory visibility zones (footer, privacy notice, rights response templates, app settings) • Verify publication accessibility for all user categories including non-logged-in users • Maintain training and internal escalation path for query resolution with service levels recorded in policy | K35: Compliant | L35: 4 | M35: No | O35: Low | P35: Verified | Q35: DPO | R35: 46006 | S35: Dedicated privacy contact published on website footer, app settings, and all privacy notices. Monthly reachability audit in place. | T35: 100000 | U35: 1 | V35: Audit-Ready | W35: Website Footer Screenshot Dec 2025; App Settings Screenshot; Privacy Notice v3.1 — SharePoint/Privacy/ | X35: 46037 | Y35: Verified by external auditor. No findings.
A36: 32 | B36: CP-02 | C36: Contact & Publication | D36: Medium | E36: Sec. 10(2), Rule 9 | F36: ₹50 Cr | G36: Section 10(2) read with Rule 9 | H36: Data Fiduciary | I36: Applicability of DPO Contact Requirement | J36: • Conduct internal and documented assessment of classification under Section 10 criteria • If classified as Significant Data Fiduciary → appoint Data Protection Officer and publish the contact • If not classified as Significant Data Fiduciary → assign and publish a trained, accountable and authorised contact person • Periodically revalidate classification status
A37: 33 | B37: CD-02 | C37: Children & Exemptions | D37: Low | E37: Sec. 9(4), 12(2) | F37: ₹200 Cr | G37: Section 9(4) read with Section 12(2) | H37: Data Fiduciary is a clinical establishment / mental health establishment / healthcare professional / Child-Care Centre/Creche/ Educational Institutions | I37: Exception Based on Class of Data Fiduciary | J37: • Document and approve class-eligibility mapping referencing Fourth Schedule language • Bind processing purpose to permitted scenario using access-control + architectural controls • Maintain necessity + proportionality evidence and periodic review trail
A38: 34 | B38: CD-03 | C38: Children & Exemptions | D38: Low | E38: Sec. 9(4), 12(2) | F38: ₹200 Cr | G38: Section 9(4) read with Section 12(2) | H38: Data Fiduciary | I38: Exception Based on Purpose | J38: • Apply purpose-matching test prior to invocation • Record purpose code, statutory basis, and necessity/proportionality justification • Maintain documentation evidencing minimal-use alignment • Hard-block scope extension, feature-addition and repurposing • Enforce periodic legal-basis re-validation for continued eligibility
A39: 35 | B39: CD-01 | C39: Children & Exemptions | D39: Critical | E39: Sec. 8(5), Rule 10 | F39: ₹200 Cr | G39: Section 8(5) read with Rule 10 | H39: Data Fiduciary | I39: Data Protection & Security Safeguards for Child Data | J39: • Implement child-specific hardened controls including encryption, segregated repositories, multi-factor authentication, tamper-resistant audit logs • Conduct structured periodic control testing with evidentiary documentation | K39: Non-Compliant | L39: 0 | M39: Yes | N39: No age-verification mechanism. No child-specific data segregation. Standard security controls applied uniformly — no hardened child-data protections. No parental consent workflow. | O39: Critical | P39: Not Started | Q39: Head of Product | R39: 46326 | S39: Implement age-gate with Rule 10 verification. Build parental consent workflow. Segregate child data repositories with enhanced encryption and MFA. Deploy tamper-resistant audit logs. | T39: 5000000 | U39: 0 | V39: Not Collected | X39: 46068 | Y39: ₹200 Cr penalty exposure. Requires significant product and infrastructure changes. Board approval needed for budget.
A40: 36 | B40: CD-04 | C40: Children & Exemptions | D40: Low | E40: Sec. 9(4), 12(1) | F40: ₹200 Cr | G40: Sec 9(4) read with Sec 12(1) | H40: Data Fiduciary under 4th Schedule hospital | I40: Exception Based on Class of Data Fiduciary | J40: Maintain documented evidence establishing correct classification under Part-A • Preserve purpose-to-schedule mapping record and necessity assessment • Prevent scope expansion, behavioural analytics, or any unrelated derivation use • Maintain evidence repository including SOPs, notices, Data Protection Impact Assessment notes, logs, and risk justification • Conduct periodic eligibility verification and re-qualification triggered by role, service, technology, vendor, or contractual change
A41: 37 | B41: CD-05 | C41: Children & Exemptions | D41: Low | E41: Sec. 9(4), 12(2) | F41: ₹200 Cr | G41: Sec 9(4) read with Sec 12(2) | H41: Data Fiduciary | I41: Exception Based on Purpose | J41: • Conduct documented purpose-match verification before exemption use • Maintain written legal basis artefact (statutory order, mandate, authorised instruction) • Apply least-data and least-function design • Prohibit profiling, analytics, enrichment, resale or secondary use • Maintain evidence including decision notes, data-flow, logs, retention and review records
A42: 38 | B42: CD-06 | C42: Children & Exemptions | D42: Low | E42: Sec. 9(4), 12(1) | F42: ₹200 Cr | G42: Sec 9(4) read with Sec 12(1) | H42: Data Fiduciary is clinical establishment / mental health establishment / healthcare professional | I42: Exemption A1 – Clinical / Mental Health / Healthcare | J42: • Retain and periodically validate clinical licence / statutory registration documents • Maintain written clinical justification linking personal data to treatment necessity • No analytics, profiling, behavioural inference, optimisation, commercial usage, marketing, or secondary use • Maintain minimum-necessary data access discipline with medical-role-based access • Maintain treatment-linked audit notes including clinician authorisation
A43: 39 | B43: CD-07 | C43: Children & Exemptions | D43: Low | E43: Sec. 9(4), 12(1) | F43: ₹200 Cr | G43: Sec 9(4) read with Sec 12(1) | H43: Data Fiduciary is an allied healthcare professional | I43: Exemption A2 – Allied Healthcare | J43: • Maintain written evidence of referral or clinician-authorised treatment plan • Restrict personal data to minimum-necessary fields directly required for treatment support • Prohibit analytics, profiling, product development, marketing, behavioural inference, or optimisation • Maintain documented access logs + authorised role mapping • Record proportionality and clinical-necessity rationale per case
A44: 40 | B44: CD-08 | C44: Children & Exemptions | D44: Low | E44: Sec. 9(4), 12(1) | F44: ₹200 Cr | G44: Sec 9(4) read with Sec 12(1) | H44: Data Fiduciary is an Educational Institution | I44: Exemption A3 – Educational Institution | J44: • Maintain written class-eligibility record showing institution status • Enforce strict purpose-locking to either educational-activity conduct or safety-interest monitoring; no mixed-purposes • Disable commercial analytics, profiling, targeted content, behavioural optimisation, or advertising • Implement minimum-data capture + least-function design • Maintain access logs + CCTV/device logs + monitoring rationale evidence • Conduct annual exemption review + trigger review on technology or purpose
A45: 41 | B45: CD-09 | C45: Children & Exemptions | D45: Low | E45: Sec. 9(4), 12(1) | F45: ₹200 Cr | G45: Sec 9(4) read with Sec 12(1) | H45: Data Fiduciary is an Creche or Childcare Centre | I45: Exemption A4 – Crèche / Child-Care Operator | J45: • Apply exclusive safety-use purpose (no learning analytics, behavioural insights, service-design inputs, parental-scoring, or commercial profiling) • Implement data minimisation, restricted retention, and zero secondary use • Ensure live-use visibility only — no long-term behavioural trend analysis • Maintain authorised-access roster + CCTV/device logs + exception logs • Configure automatic deletion window aligned to safety-need expiry • Conduct annual re-validation + change-trigger reassessmen
A46: 42 | B46: CD-10 | C46: Children & Exemptions | D46: Low | E46: Sec. 9(4), 12(1) | F46: ₹200 Cr | G46: Sec 9(4) read with Sec 12(1) | H46: Data Fiduciary mandating Entity for child Transport | I46: Exemption A5 – Transport Entity | J46: • Activate tracking only during active transit window (boarding → drop-off confirmation) • No analytical profiling, historical trend creation, or retention beyond immediate safety use • Store no historical location repository unless mandated under a specific written legal order • Authorised-person access only (transport control desk / safety officer) with access logging • Configure automatic termination + deletion upon trip closure • Maintain tamper-proof access and event logs for audit verifica
A47: 43 | B47: CD-11 | C47: Children & Exemptions | D47: Low | E47: Sec. 9(4), 12(2) | F47: ₹200 Cr | G47: Sec 9(4) read with Sec 12(2) | H47: Data Fiduciary processing to provide Govt. Scheme Benefits | I47: Exemption B2 – Purpose: Subsidy / Public Funds | J47: • Maintain written reference to enabling legal instrument (scheme notification / GR / order / law) • Process data strictly limited to eligibility verification, disbursement, utilisation and audit trail • No analytics, profiling, cross-scheme sharing, commercial enrichment, or benefit-optimisation modelling • Maintain processing logs + justification memo for necessity and proportionality
A48: 44 | B48: CD-12 | C48: Children & Exemptions | D48: Low | E48: Sec. 9(4), 12(2) | F48: ₹200 Cr | G48: Sec 9(4) read with Sec 12(2) | H48: Significant Data Fiduciary | I48: Exemption B3 – Purpose: Email Account | J48: • Limit processing strictly to account creation, login, credential management, communication enablement and security functions • No ads, profiling, recommender systems, ranking, behavioural scoring, engagement-optimisation, or function expansion • Disable monetisation, sponsored content, targeted notifications, or data-based personalisation • Store and process minimum mandatory identifiers only • Maintain audit artefacts proving strict conformity.
A49: 45 | B49: CD-13 | C49: Children & Exemptions | D49: Low | E49: Sec. 9(4), 12(2) | F49: ₹200 Cr | G49: Section 9(4) read with Section 12(2) | H49: Data Fiduciary | I49: Exemption B4 – Purpose: Real-Time Location Safety | J49: • Restrict collection + processing to live, real-time location only • Prohibit storage, caching, history creation, trajectory mapping, heat-mapping, replay or route intelligence • No analytical, predictive, forensic, advertising, behavioural, policing, or service-expansion use • Auto-terminate tracking immediately upon end of risk/safety event or session • Enforce access-control whitelist limited to authorised safety personnel • Maintain audit proof of real-time-only processing and auto-disable
A50: 46 | B50: CD-14 | C50: Children & Exemptions | D50: Low | E50: Sec. 9(4), 12(2) | F50: ₹200 Cr | G50: Sec 9(4) read with Sec 12(2) | H50: Significant Data Fiduciary | I50: Exemption B5 – Purpose: Preventing Harmful Content | J50: • Implement system-level or network-layer content blocking controls only • No user-level targeting, behavioural analysis, scoring, interest mining, predictive filtering, sentiment inference, risk-profiling, or algorithmic segmentation • No retention, enrichment, or dataset building from blocked content events • Maintain audit trail evidencing non-profiling, non-personalised, non-behavioural approach • Apply least-function design—no commercial, advertising, marketing, optimisation, engagement, re
A51: 47 | B51: CD-15 | C51: Children & Exemptions | D51: Low | E51: Sec. 9(4), 12(2) | F51: ₹200 Cr | G51: Sec 9(4) read with Sec 12(2) | H51: Significant Data Fiduciary | I51: Exemption B6 – Purpose: Age Confirmation (Rule 10) | J51: • Process personal data strictly and only to complete age-confirmation workflow • No secondary use, no enrichment, no inferencing, no behavioural, biometric, psychometric, or device-fingerprinting-based scoring • Delete artefacts, logs, training signals, and by-products immediately after confirmation outcome is issued, unless retention is legally mandatory and documented • Maintain verifiable evidence that no analytics, profiling, optimisation, ranking, or commercial inference models are run • A
A52: 48 | B52: CD-16 | C52: Children & Exemptions | D52: Low | E52: Sec. 9(4), 12(2) | F52: ₹200 Cr | G52: Section 9(4) read with Section 12(2) | H52: Significant Data Fiduciary | I52: Exemption – Purpose B6 (Age Confirmation / Rule-10 Due Diligence) | J52: • Use verification data only for age confirmation • Delete artefacts & by-products immediately post-verification • No storage, profiling, optimisation, enrichment, or model-training • No reuse across services, sessions, platforms, or affiliates
A53: 49 | B53: SDF-01 | C53: SDF Obligations | D53: Critical | E53: Sec. 10(1), Rule 13 | F53: ₹150 Cr | G53: Section 10(1) Read with Rule 13 | H53: Significant Data Fiduciary | I53: Appointment of Data Protection Officer (DPO) | J53: • Issue Board-approved DPO appointment resolution • Document reporting line to Board/Governing Body • Update governance, RACI & conflict-free mandate • Publish DPO business contact details | K53: Not Applicable | L53: 0 | M53: No | N53: Organisation not notified as SDF by Central Government. Monitoring notification status. Pre-positioning resources as precautionary measure. | O53: Low | S53: Monitoring CG notifications. Internal readiness assessment completed. DPO appointment framework documented for activation if/when notified. | V53: Collected | W53: SDF Readiness Assessment Memo — SharePoint/Privacy/SDF/ | X53: 46054 | Y53: Not currently applicable. Re-assess quarterly.
A54: 50 | B54: SDF-02 | C54: SDF Obligations | D54: High | E54: Sec. 10(1), Rule 13(1-2) | F54: ₹150 Cr | G54: Section 10(1) Read with Rule 13(1) , 13(2) | H54: Significant Data Fiduciary | I54: Appointment of Independent Data Auditor | J54: • Execute engagement with qualified and independent auditor • Maintain independence declaration and SoW • Define audit calendar, scope, methodology, artefact repository and submission deliverables
A55: 51 | B55: SDF-03 | C55: SDF Obligations | D55: High | E55: Sec. 10(2)(c)(i), Rule 13(1) | F55: ₹150 Cr | G55: Section 10(2)(c)(i) read with Rule 13(1) | H55: Significant Data Fiduciary | I55: Mandatory Annual DPIA | J55: • Establish annual DPIA calendar • Apply approved DPIA framework (scope → processing → risk → mitigation) • Place findings before Board/ Governing Body where required
A56: 52 | B56: SDF-04 | C56: SDF Obligations | D56: High | E56: Sec. 10(2)(c)(ii), Rule 13(1) | F56: ₹150 Cr | G56: Section 10(2)(c)(ii) read with Rule 13(1) | H56: Significant Data Fiduciary | I56: Mandatory Annual Audit | J56: • Maintain audit findings register • Track audit remediation & closure SLA • Escalate unresolved items to senior management • Engage Board accepted Audit Professionals.
A57: 53 | B57: SDF-05 | C57: SDF Obligations | D57: Medium | E57: Sec. 10(2), Rule 13(2) | F57: ₹150 Cr | G57: Section 10(2) read with Rule 13(2) | H57: Significant Data Fiduciary | I57: Regulatory Reporting of DPIA + Audit | J57: • Prepare final DPIA and audit observations report • Use Board-approved reporting format • Secure timestamped submission record • Retain Board acknowledgement evidence
A58: 54 | B58: SDF-06 | C58: SDF Obligations | D58: Medium | E58: Sec. 8(5), Rule 13(3) | F58: ₹150 Cr | G58: Section 8(5) read with Rule 13(3) | H58: Significant Data Fiduciary | I58: Technical Due-Diligence for Algorithmic & Software Risks | J58: • Conduct algorithmic/systemic risk assessment • Assess risk associated/might be present to Data Principal Rights• Maintain model explainability & documentation • Perform pre-production privacy, security & resilience testing • Validate vendor controls if outsourced
A59: 55 | B59: SDF-07 | C59: SDF Obligations | D59: Medium | E59: Rule 13(4-5) | F59: ₹150 Cr | G59: Rule 13(4) read with Rule 13(5) | H59: Data Fiduciary transferring Personal Data to outside India | I59: Data + Traffic Flow Localisation (If Specified) | J59: Maintain updated data-flow register and asset-to-location mapping • Implement in-India hosting, routing, backup and disaster-recovery pathways • Apply network-level and IAM-level geo-blocking for export pathways • Maintain evidence of localisation controls and periodic compliance testing
A60: 56 | B60: DPR-01 | C60: Data Principal Rights | D60: High | E60: Sec. 11-14, Rule 14(1) | F60: ₹50 Cr | G60: Section 11-14 read with Rule 14(1) | H60: Data Fiduciary | I60: Rights Request Enablement & Publishing Requirement | J60: • Publish rights request submission methods on website/app • Provide clear accepted identifiers list and validation steps • Ensure interface availability without friction • Maintain version-controlled publication record | K60: Partially Compliant | L60: 2 | M60: Yes | N60: Rights request form exists on website but not in mobile app. Identifier validation is manual. No SLA tracking. Publication does not include all Rule 14 elements. | O60: Medium | P60: In Progress | Q60: DPO | R60: 46218 | S60: Extend rights request portal to mobile app. Automate identity verification. Implement SLA tracking dashboard. Update published information to include all Rule 14(1) elements. | T60: 1800000 | U60: 0.3 | V60: Collected | W60: Rights Portal Screenshots; Current SOP — SharePoint/Privacy/Rights/ | X60: 46063 | Y60: Web portal functional. Mobile app integration in sprint planning.
A61: 57 | B61: DPR-02 | C61: Data Principal Rights | D61: Medium | E61: Sec. 11(1), Rule 14(2) | F61: ₹50 Cr | G61: Section 11(1) read with Rule 14(2) | H61: Data Fiduciary | I61: Rights Request Submission Path | J61: • Use one controlled intake mechanism for all rights requests • Capture and store timestamp, submission channel, requester identifier, and linked consent record • Reject or re-route non-standard submissions with guidance to correct channel
A62: 58 | B62: DPR-03 | C62: Data Principal Rights | D62: Medium | E62: Sec. 11, Rule 14(1)(b) | F62: ₹50 Cr | G62: Section 11 read with Rule 14(1)(b) | H62: Data Fiduciary | I62: Rights-Enabling Identifier Requirements | J62: • Maintain authoritative identifier registry with lifecycle controls• Apply mandatory identity verification before processing any rights request• Use multi-factor evidence checks where risk or sensitivity is high• Log identity verification method + proof before request is accepted
A63: 59 | B63: DPR-04 | C63: Data Principal Rights | D63: Medium | E63: Sec. 11(1)(a-c), Rule 14 | F63: ₹50 Cr | G63: Section 11(1)(a)-(c) read with Rule 14 | H63: Data Fiduciary | I63: Rights Response Content – Right to Access | J63: • Issue standardised, structured, machine-readable access report (portal/App) • Include data categories, purpose, processing actions, retention status, lawful basis & recipient registry • Clearly mark legal-exclusion cases • Maintain audit log (identifier used, timestamp, disclosure scope)
A64: 60 | B64: DPR-05 | C64: Data Principal Rights | D64: High | E64: Sec. 12(1-3), Rule 14 | F64: ₹50 Cr | G64: Section 12(1)-(3) read with Rule 14 | H64: Data Fiduciary | I64: Rights to Correction, Completion, Updating & Erasure | J64: • Provide digital and verifiable request channel • Validate identity + scope before processing the request • For erasure, verify retention necessity under law/contract/ongoing purpose • Synchronise corrections or deletions across all linked systems and processors • Maintain immutable evidence log (request → decision → action timestamp)
A65: 61 | B65: DPR-06 | C65: Data Principal Rights | D65: High | E65: Sec. 13(1-3), Rule 14(3) | F65: ₹50 Cr | G65: Section 13(1)-(3) read with Rule 14(3) | H65: Data Fiduciary | I65: Grievance Redress System Obligations | J65: • Maintain accessible and recordable channels (portal/app/email/ticketing) • Publish grievance contacts + workflow • Acknowledge, track, and close within ≤ 90 days • Maintain complete audit evidence (ticket ID, timestamps, comms, closure record) • Notify processors/partners where outcome impacts processing
A66: 62 | B66: DPR-07 | C66: Data Principal Rights | D66: Medium | E66: Sec. 14(1-2), Rule 14(4) | F66: ₹50 Cr | G66: Section 14(1)-(2) read with Rule 14(4) | H66: Data Fiduciary | I66: Nomination Rights | J66: • Provide secure digital nomination interface (portal/form) • Capture nominee identity using validated identifiers • Maintain tamper-proof nomination record including timestamp, version, and link to DP profile • Provide update/revocation workflow with audit logs • Establish activation protocol for nominee after proof of death or incapacity
A67: 63 | B67: DPR-08 | C67: Data Principal Rights | D67: Medium | E67: Sec. 13, Rule 14(3) | F67: ₹50 Cr | G67: Section 13 read with Rule 14(3) | H67: Data Fiduciary /Consent Managers | I67: Publishing of Time-Bound Grievance Response Capability | J67: • Display grievance channel + SLA prominently • Auto-acknowledge ticket with reference ID
A68: 64 | B68: CBT-01 | C68: Cross-Border Transfer | D68: High | E68: Sec. 16(1), Rule 15 | F68: ₹50 Cr | G68: Section 16 (1)read with Rule 15 | H68: Data Fiduciary | I68: Cross-Border Personal Data Transfer Enablement | J68: • Maintain Cross-Border Data Transfer Policy • Conduct destination country regulatory + adequacy assessment • Allow transfer only if no restrictive notification applies • Implement whitelist/blacklist controls in systems • Obtain contractual + security safeguards from recipient • Maintain transfer approval + evidence file | K68: Partially Compliant | L68: 1 | M68: Yes | N68: Cross-border transfer policy drafted but not approved. Data flow mapping incomplete — 3 of 7 processors with overseas operations not yet assessed. No whitelist/blacklist controls in systems. | O68: High | P68: In Progress | Q68: Head of Legal | R68: 46249 | S68: Complete data flow mapping for all 7 overseas processors. Finalise and Board-approve cross-border transfer policy. Implement system-level geo-blocking controls. Conduct destination country adequacy assessments. | T68: 1500000 | U68: 0.2 | V68: Not Collected | X68: 46068 | Y68: Policy draft with Legal. Data flow mapping 40% complete.
A69: 65 | B69: CBT-02 | C69: Cross-Border Transfer | D69: Medium | E69: Sec. 16(2), Rule 15 | F69: ₹50 Cr | G69: Section 16 (2)read with Rule 15 | H69: Data Fiduciary | I69: Compliance With Higher Restriction Laws | J69: • Map all Indian cross-border rules (RBI, IRDAI, SEBI, MeitY, CERT-In, UIDAI, etc.) • Enforce multi-layer legal compatibility test before transfer • Maintain sector-specific compliance register
A70: 66 | B70: RA-01 | C70: Research & Archiving | D70: Low | E70: Sec. 17(2)(b), Rule 16 | F70: ₹50 Cr | G70: Section 17 (2)(b) read with Rule 16 | H70: Data Fiduciary Engaged in Processing Personal Data for research, archiving, or statistical purposes | I70: Eligibility for Research / Archiving / Statistical Exemption | J70: • Conduct eligibility assessment checklist • Prepare written exemption justification memo • Approve via privacy + legal workflow
A71: 67 | B71: RA-02 | C71: Research & Archiving | D71: Low | E71: Sec. 17(2)(b), Rule 16 | F71: ₹50 Cr | G71: Section 17 (2)(b) read with Rule 16 | H71: Data Fiduciary Engaged in Processing Personal Data for research, archiving, or statistical purposes | I71: Lawfulness of Research Processing | J71: • Maintain written legal basis note before ingest • Confirm no repurposing into commercial profiling, credit, insurance, eligibility or marketing
A72: 68 | B72: RA-03 | C72: Research & Archiving | D72: Low | E72: Sec. 17(2)(b), Rule 16 | F72: ₹50 Cr | G72: Section 17 (2)(b) read with Rule 16 | H72: Data Fiduciary Engaged in Processing Personal Data for research, archiving, or statistical purposes | I72: Personal Data Minimisation Requirement | J72: • Use data minimisation matrix • Apply masking, tokenisation, or sampling where feasible
A73: 69 | B73: RA-04 | C73: Research & Archiving | D73: Low | E73: Sec. 17(2)(b), Rule 16 | F73: ₹50 Cr | G73: Section 17 (2)(b) read with Rule 16 | H73: Data Fiduciary Engaged in Processing Personal Data for research, archiving, or statistical purposes | I73: Accuracy, Completeness & Consistency | J73: • Implement data validation + de-duplication ruleset • Log and correct data quality exceptions
A74: 70 | B74: RA-05 | C74: Research & Archiving | D74: Low | E74: Sec. 17(2)(b), Rule 16 | F74: ₹50 Cr | G74: Section 17 (2)(b) read with Rule 16 | H74: Data Fiduciary Engaged in Processing Personal Data for research, archiving, or statistical purposes | I74: Retention Limitation | J74: • Define retention period at project start • Enable auto-purge + deletion certificate workflow
A75: 71 | B75: RA-06 | C75: Research & Archiving | D75: Low | E75: Sec. 17(2)(b), Rule 16 | F75: ₹50 Cr | G75: Section 17 (2)(b) read with Rule 16 | H75: Data Fiduciary Engaged in Processing Personal Data for research, archiving, or statistical purposes | I75: Security Safeguards | J75: • Store data in segregated research zone • Enforce RBAC, MFA, encryption, logging, export controls
A76: 73 | B76: RA-07 | C76: Research & Archiving | D76: Low | E76: Sec. 17(2)(b), Rule 16 | F76: ₹50 Cr | G76: Section 17 (2)(b) read with Rule 16 | H76: Data Fiduciary Engaged in Processing Personal Data for research, archiving, or statistical purposes | I76: Accountability Obligation | J76: • Assign Research Data Owner + Data Steward roles • Maintain full compliance evidence repository
A77: 74 | B77: GR-01 | C77: Govt. Information Requests | D77: Critical | E77: Sec. 36, Rule 23 | F77: ₹250 Cr | G77: Section 36 read with Rule 23 | H77: Data Fiduciary | I77: Furnishing Information to Central Government | J77: • Maintain Regulatory Request Handling SOP • Verify request authority + purpose alignment • Use secure, logged transmission • Maintain confidentiality where directed • Record evidence + chain-of-custody in compliance register
A79: ASSESSMENT SUMMARY
B81: OVERALL READINESS | G81: Score | H81: Max
B82: Overall Maturity Score | E82: % Complete | G82: =SUM(L5:L77) -> 15 | H82: =COUNTA(A5:A77)*4 -> 292
B83: Critical Controls | E83: =IF(H83=0,0,G83/H83) -> 0.17857143 | G83: {=SUMPRODUCT((D5:D77="Critical")*L5:L77)} -> 5 | H83: =COUNTIF(D5:D77,"Critical")*4 -> 28
B84: High Controls | E84: =IF(H84=0,0,G84/H84) -> 0.068181818 | G84: {=SUMPRODUCT((D5:D77="High")*L5:L77)} -> 6 | H84: =COUNTIF(D5:D77,"High")*4 -> 88
B85: Medium Controls | E85: =IF(H85=0,0,G85/H85) -> 0.05 | G85: {=SUMPRODUCT((D5:D77="Medium")*L5:L77)} -> 4 | H85: =COUNTIF(D5:D77,"Medium")*4 -> 80
B86: Low Controls | E86: =IF(H86=0,0,G86/H86) -> 0 | G86: {=SUMPRODUCT((D5:D77="Low")*L5:L77)} -> 0 | H86: =COUNTIF(D5:D77,"Low")*4 -> 96
E87: =IF(H82=0,0,G82/H82) -> 0.051369863
B89: CATEGORY BREAKDOWN | G89: Avg Maturity | H89: Controls
B90: Consent & Notice | G90: =IFERROR(AVERAGEIF(C5:C77,"Consent & Notice",L5:L77),0) -> 1.5 | H90: =COUNTIF(C5:C77,"Consent & Notice") -> 5
B91: Consent Manager | G91: =IFERROR(AVERAGEIF(C5:C77,"Consent Manager",L5:L77),0) -> 0 | H91: =COUNTIF(C5:C77,"Consent Manager") -> 6
B92: Security Safeguards | G92: =IFERROR(AVERAGEIF(C5:C77,"Security Safeguards",L5:L77),0) -> 2 | H92: =COUNTIF(C5:C77,"Security Safeguards") -> 7
B93: Breach Notification | G93: =IFERROR(AVERAGEIF(C5:C77,"Breach Notification",L5:L77),0) -> 0 | H93: =COUNTIF(C5:C77,"Breach Notification") -> 7
B94: Retention & Erasure | G94: =IFERROR(AVERAGEIF(C5:C77,"Retention & Erasure",L5:L77),0) -> 3 | H94: =COUNTIF(C5:C77,"Retention & Erasure") -> 5
B95: Children & Exemptions | G95: =IFERROR(AVERAGEIF(C5:C77,"Children & Exemptions",L5:L77),0) -> 0 | H95: =COUNTIF(C5:C77,"Children & Exemptions") -> 16
B96: SDF Obligations | G96: =IFERROR(AVERAGEIF(C5:C77,"SDF Obligations",L5:L77),0) -> 0 | H96: =COUNTIF(C5:C77,"SDF Obligations") -> 7
B97: Data Principal Rights | G97: =IFERROR(AVERAGEIF(C5:C77,"Data Principal Rights",L5:L77),0) -> 2 | H97: =COUNTIF(C5:C77,"Data Principal Rights") -> 8
B98: Cross-Border Transfer | G98: =IFERROR(AVERAGEIF(C5:C77,"Cross-Border Transfer",L5:L77),0) -> 1 | H98: =COUNTIF(C5:C77,"Cross-Border Transfer") -> 2
B99: Research & Archiving | G99: =IFERROR(AVERAGEIF(C5:C77,"Research & Archiving",L5:L77),0) -> 0 | H99: =COUNTIF(C5:C77,"Research & Archiving") -> 7
B100: Contact & Publication | G100: =IFERROR(AVERAGEIF(C5:C77,"Contact & Publication",L5:L77),0) -> 4 | H100: =COUNTIF(C5:C77,"Contact & Publication") -> 2
B101: Govt. Information Requests | G101: =IFERROR(AVERAGEIF(C5:C77,"Govt. Information Requests",L5:L77),0) -> 0 | H101: =COUNTIF(C5:C77,"Govt. Information Requests") -> 1

Sheet Granular Controls
A1: DPDP COMPLIANCE FRAMEWORK — GRANULAR CONTROL ASSESSMENT WITH TRACKING
A2: Sr. No. | B2: Ref. Act | C2: Ref. Rule | D2: Act Description | E2: Rule Description | F2: Nature of Activity | G2: Applicability | H2: Assessment Status | I2: Maturity Level | J2: Impl. Status | K2: Accountable Owner | L2: Target Date | M2: Risk Rating | N2: Evidence Status
A3: A1.1 | B3: Sec 5(1) | C3: Rule 4(1) | D3: Notice must describe categories of personal data and the purpose before/with consent. | E3: Mandatory notice elements including purpose, data categories, rights, grievance details. | F3: Draft and Serve Privacy Notice | G3: DF + SDF
A4: A1.2 | B4: Sec 5(1)(ii) | C4: Rule 4(2)(a) | D4: Notice must inform DP of rights under Sec 6(4) and Sec 13. | E4: DF must publish DP rights mechanisms. | F4: Publish Rights Exercise Procedure | G4: DF + SDF
A5: A1.3 | B5: Sec 5(1)(iii) | C5: Rule 4(2)(b) | D5: Notice must specify grievance mechanism and contact. | E5: DF must publish grievance timelines + contacts within 90 days. | F5: Publish Grievance Redress Details | G5: DF + SDF
A6: A1.4 | B6: Sec 5(3) | C6: Rule 4(1) | D6: Notice must be available in English or Eighth Schedule language. | E6: Supports multilingual availability. | F6: Multilingual Notice Availability | G6: DF + SDF
A7: A1.5 | B7: Sec 5(2) | C7: Rule 4(3) | D7: DF must issue fresh notice for pre-Act consent. | E7: Sets format/timeline for legacy notices. | F7: Legacy Consent Notice Issuance | G7: DF + SDF
A8: A1.6 | B8: Sec 5 | C8: Rule 14(1) | D8: Notice must include DF/DPO contact info. | E8: Requires publication on website/app. | F8: Publish DF/DPO Contact Details | G8: DF + SDF
A9: A1.7 | B9: Sec 5 + Sec 6(3) | C9: Rule 4 | D9: Notice must be separate from T&Cs and clearly structured. | E9: Rule enforces clarity and plain language. | F9: Separate Notice from T&Cs | G9: DF + SDF
A10: Sr. No. (A2 — Consent Requirements)
A11: A2.1 | B11: Sec 6(1) | C11: — | D11: Consent must be free, specific, informed, unambiguous, affirmative. | E11: — | F11: Valid Consent Capture | G11: DF + SDF
A12: A2.2 | B12: Sec 6(1) | C12: Rule 4 | D12: Consent must be purpose-limited. | E12: Rule supports segmentation of notice items. | F12: Purpose-limited Consent Design | G12: DF + SDF
A13: A2.3 | B13: Sec 6(2) | C13: — | D13: Any unlawful portion of consent is void. | E13: — | F13: Consent Validity Review | G13: DF + SDF
A14: A2.4 | B14: Sec 6(3) | C14: Rule 4 | D14: Consent request must be clear, plain language. | E14: Rule mandates simple and readable format. | F14: Plain-language Consent Request | G14: DF + SDF
A15: A2.5 | B15: Sec 6(3) | C15: Rule 4 | D15: Consent request must include DF/DPO contact. | E15: Requires accessible publication. | F15: Include Contact in Consent Request | G15: DF + SDF
A16: A2.6 | B16: Sec 6(4) | C16: Rule 14 | D16: Withdrawal must be as easy as giving consent. | E16: Requires DF to publish mechanism within 90 days. | F16: Consent Withdrawal Mechanism | G16: DF + SDF
A17: A2.7 | B17: Sec 6(5) | C17: — | D17: DF must stop processing when consent withdrawn unless legally required otherwise. | E17: — | F17: Stop Processing After Withdrawal | G17: DF + SDF
A18: A2.8 | B18: Sec 6(6) | C18: Rule 8 | D18: DF must ensure processors cease processing on withdrawal. | E18: Rule ties this to erasure obligations. | F18: Processor Cessation Instruction | G18: DF (via contract)
A19: A2.9 | B19: Sec 6(7) | C19: Rule 7 | D19: DP may use a Consent Manager to give/manage consent. | E19: Rule defines Consent Manager duties + registration. | F19: Integrate Consent Manager | G19: DF + SDF
A20: A2.10 | B20: Sec 6(8) | C20: Rule 7 | D20: Consent Managers must act only on DP instructions; accountable to DP. | E20: Rule outlines CM transparency + logs. | F20: Ensure CM Accountability | G20: Consent Manager
A21: A2.11 | B21: Sec 6(10) | C21: — | D21: DF must prove notice + consent validity if challenged. | E21: — | F21: Maintain Consent Logs & Evidence | G21: DF + SDF
A22: Sr. No. (A3 — Voluntary Data Supply)
A23: A3.1 | B23: Sec 7(a) | C23: Rule 4 | D23: DF may process voluntarily supplied data for a specific purpose unless DP objects. | E23: Notice obligations still apply for voluntary data. | F23: Voluntary Data Processing | G23: DF + SDF
A24: A3.2 | B24: Sec 7(a) Illustration | C24: — | D24: DF must cease processing when DP objects. | E24: — | F24: Opt-out Handling | G24: DF + SDF
A25: Sr. No. (A4 — Children / PWD Requirements)
A26: A4.1 | B26: Sec 9(1) | C26: Rule 12 | D26: Must obtain verifiable parental/guardian consent before processing child/PWD data. | E26: Sets verification rules + exemptions (Fourth Schedule). | F26: Parental/Guardian Consent Mechanism | G26: DF + SDF
A27: A4.2 | B27: Sec 9(3) | C27: Fourth Schedule | D27: No tracking, monitoring, profiling, targeted ads for children. | E27: Fourth Schedule exemptions for safety/education. | F27: Child-protective Processing Controls | G27: DF + SDF
A28: Sr. No. (A5 — Publication & Accessibility Requirements)
A29: A5.1 | B29: Sec 5(3) | C29: Rule 14 | D29: Notice must be in English or Eighth Schedule language. | E29: Requires DF to publish grievance + rights info. | F29: Multilingual Publication | G29: DF + SDF
A30: A5.2 | B30: Sec 6(3) | C30: Rule 14 | D30: DF/DPO contact must be easily accessible. | E30: Publication on website/app mandatory. | F30: Publish DF/DPO Contact | G30: DF + SDF
A31: Sr. No. (A6 — Consent Logs, Withdrawal Evidence & UI/UX Controls)
A32: A6.1 | B32: Sec 6(10) | C32: — | D32: DF must prove that notice was given and consent was obtained validly. | E32: — | F32: Maintain Consent Evidence Repository | G32: DF + SDF
A33: A6.2 | B33: Sec 6(1) | C33: Rule 4 | D33: UI must capture consent as a clear affirmative action; no pre-ticked boxes or implied consent. | E33: Rule enforces consent to be explicit and unambiguous. | F33: UI/UX Consent Capture Control | G33: DF + SDF
A34: A6.3 | B34: Sec 6(1), Sec 6(3) | C34: Rule 4 | D34: Consent UI must be in clear and plain language. | E34: Rule mandates readability and user-friendly formatting. | F34: Consent UI Readability Standard | G34: DF + SDF
A35: A6.4 | B35: Sec 6(1) | C35: Rule 4 | D35: Consent must be purpose-specific; UI must clearly separate each purpose. | E35: Rule requires detailing of data categories and purposes. | F35: Granular Purpose-wise Consent Options | G35: DF + SDF
A36: A6.5 | B36: Sec 6(3) | C36: — | D36: UI must provide option to access notice in English or Eighth Schedule language. | E36: Rule requires notices in all supported languages. | F36: Multilingual Consent UI Availability | G36: DF + SDF
A37: A6.6 | B37: Sec 6(4) | C37: Rule 14 | D37: Withdrawal must be as easy as giving consent — same UI channel or equivalent. | E37: Requires published withdrawal mechanism within 90 days. | F37: Withdrawal UI/UX Parity Control | G37: DF + SDF
A38: A6.7 | B38: Sec 6(5) | C38: — | D38: UI must clearly indicate the consequences of withdrawal. | E38: — | F38: Withdrawal Consequences Disclosure | G38: DF + SDF
A39: A6.8 | B39: Sec 6(6) | C39: Rule 8 | D39: Processor must cease processing when consent is withdrawn; DF must document this in logs. | E39: Rule aligns withdrawal with erasure instruction obligations. | F39: Processor Withdrawal Log & Instruction Record | G39: DF (via contract)
A40: A6.9 | B40: Sec 6(10) | C40: — | D40: Consent logs must be timestamped and attributable to the DP. | E40: — | F40: Timestamped Consent Capture Logs | G40: DF + SDF
A41: A6.10 | B41: Sec 6(10) | C41: — | D41: DF must maintain immutable logs of consent withdrawals. | E41: — | F41: Withdrawal Evidence Retention | G41: DF + SDF
A42: A6.11 | B42: Sec 6(7), 6(8) | C42: Rule 7 | D42: If DP uses a Consent Manager, DF must store CM tokens/messages as evidence. | E42: Rule sets CM transparency + action-logging obligations. | F42: CM-based Consent Activity Logging | G42: DF + SDF + CM
A43: A6.12 | B43: Sec 8(3) | C43: Rule 4, Rule 5 | D43: When personal data is disclosed to another DF upon consent, DF must verify logs for completeness and accuracy. | E43: Rule reinforces accuracy obligations. | F43: Consent Verification Before Data Disclosure | G43: DF + SDF
... A51: A6.20 | B51: Sec 6(5) | C51: — | D51: UI must provide fallback instructions where legal retention overrides withdrawal. | E51: — | F51: Retention Exception Display | G51: DF + SDF
A52: Sr. No. (A7 — Advanced Consent Operations & Auditability)
A53: A7.1 | B53: Sec 6(10) | C53: — | D53: DF must produce consent evidence when challenged by DP/Board. | E53: — | F53: Consent Audit Trail Maintenance | G53: DF + SDF
A54: A7.2 | B54: Sec 6(10) | C54: — | D54: DF must maintain immutable logs of consent grants, revisions, withdrawals. | E54: — | F54: Immutable Consent Log System | G54: DF + SDF
A55: A7.3 | B55: Sec 6(4) | C55: Rule 14 | D55: Withdrawal workflow must be end-to-end automated (initiation → processing stop → processor instruction). | E55: Rule requires withdrawal mechanism to be published within 90 days. | F55: Automated Withdrawal Workflow | G55: DF + SDF
A56: A7.4 | B56: Sec 6(6) | C56: Rule 8 | D56: DF must notify processors to stop processing and erase data once consent is withdrawn, and record confirmation. | E56: Rule ties processor obligations to DF instructions. | F56: Processor Withdrawal Confirmation Tracking | G56: DF (contractually on DP)
A57: A7.5 | B57: Sec 8(3) | C57: Rule 4 | D57: DF must ensure consent logs are accurate before sharing data with another DF. | E57: Rule reinforces accuracy obligations. | F57: Pre-disclosure Consent Verification | G57: DF + SDF
A58: A7.6 | B58: Sec 6(7) | C58: Rule 7 | D58: When consent comes via Consent Manager, DF must align its logs with CM timestamp and identifiers. | E58: Rule mandates CM traceability + transparency. | F58: CM–DF Consent Synchronization | G58: DF + SDF + CM
A59: A7.7 | B59: Sec 6(1) | C59: Rule 4 | D59: Consent captured offline (paper, call, in-person) must be digitized and logged equivalently. | E59: Rule requires uniform clarity + accessibility. | F59: Offline-to-Digital Consent Logging | G59: DF + SDF
A60: A7.8 | B60: Sec 6(3) | C60: Rule 4 | D60: Multiple consent surfaces (app, web, POS, call-centre) must use consistent language and purpose definitions. | E60: Rule enforces plain-language and consistency. | F60: Multi-channel Consent Harmonization | G60: DF + SDF
A61: A7.9 | B61: Sec 5(1) | C61: Rule 4 | D61: DF must store a copy of the notice version shown to the DP at the time of consent. | E61: Rule mandates clarity + version handling. | F61: Notice Version Control Storage | G61: DF + SDF
A62: A7.10 | B62: Sec 6(1) | C62: — | D62: Consent validity must be reconfirmed if DF changes purpose or expands data categories. | E62: — | F62: Consent Revalidation Workflow | G62: DF + SDF
A63: A7.11 | B63: Sec 5 + 6 | C63: Rule 4 | D63: Consent capture must be decoupled from account creation, login or service access unless strictly necessary. | E63: Rule discourages bundled consent. | F63: No Bundled Consent Enforcer | G63: DF + SDF
A64: A7.12 | B64: Sec 6(4) | C64: Rule 14 | D64: Withdrawal instructions must be acknowledged and timestamped. | E64: Requires publication of mechanism. | F64: Withdrawal Acknowledgement Workflow | G64: DF + SDF
... A77: A7.25 | B77: Sec 6(10) | C77: — | D77: DF must retain consent and withdrawal evidence for the entire duration personal data is processed. | E77: — | F77: Consent Evidence Retention | G77: DF + SDF
A78: Sr. No. (A8 — System-Level Consent & Notice Adjacent Controls)
A79: A8.1 | B79: Sec 5(1) | C79: Rule 4 | D79: Notice must remain accessible to DP after consent is provided. | E79: Rule supports persistent visibility of notice components. | F79: Persistent Notice Display Post-Consent | G79: DF + SDF
A80: A8.2 | B80: Sec 5 + 6 | C80: Rule 4 | D80: APIs, SDKs, embedded widgets must follow same notice + consent rules as native app. | E80: Rule enforces uniform implementation. | F80: Third-party API/SDK Consent Compliance | G80: DF + SDF
A81: A8.3 | B81: Sec 6(1) | C81: — | D81: Session-level processing must not begin before consent verification. | E81: — | F81: Pre-processing Consent Check in Sessions | G81: DF + SDF
A82: A8.4 | B82: Sec 6(3) | C82: Rule 4 | D82: Consent notice must be available within any embedded/webview flow. | E82: Plain-language, clear presentation required. | F82: Webview / Embedded Consent Compliance | G82: DF + SDF
A83: A8.5 | B83: Sec 6(4) | C83: Rule 14 | D83: Email/SMS consent capture must include a valid, accessible withdrawal link/path. | E83: Rule requires withdrawal mechanism to be published. | F83: Email/SMS Withdrawal Enablement | G83: DF + SDF
A84: A8.6 | B84: Sec 6(1) | C84: Rule 4 | D84: Consent must not be obtained via system nudges: pop-ups that block functionality without justification. | E84: Plain language + fairness requirement. | F84: Anti-Coercive Consent UX Pattern | G84: DF + SDF
A85: A8.7 | B85: Sec 5(3) | C85: Rule 14 | D85: Alternate interface (IVR, call, kiosk) must allow notice + consent in supported languages. | E85: Rule: multilingual accessibility. | F85: Multi-interface Multilingual Notice Support | G85: DF + SDF
A86: A8.8 | B86: Sec 6(10) | C86: — | D86: System must retain consent metadata (IP, timestamp, channel, device) when obtained digitally. | E86: — | F86: Consent Metadata Capture | G86: DF + SDF
A87: A8.9 | B87: Sec 6(10) | C87: — | D87: Logs must differentiate between fresh consent, renewed consent, updated consent. | E87: — | F87: Consent Type Classification Logging | G87: DF + SDF
A88: A8.10 | B88: Sec 6 | C88: Rule 4 | D88: Consent expiry/staleness rules must be configured (e.g., inactivity thresholds). | E88: Rule enables periodic reviews. | F88: Consent Staleness Review | G88: DF + SDF
A89: A8.11 | B89: Sec 8(3) | C89: Rule 4 | D89: Before processing for new purpose, DF must validate compatibility and obtain fresh consent. | E89: Rule addresses updated purposes. | F89: Purpose Expansion Validation | G89: DF + SDF
A90: A8.12 | B90: Sec 8(4) | C90: Rule 8 | D90: When data quality checks fail, consent must be revalidated. | E90: Rule links accuracy with processing continuation. | F90: Consent Revalidation on Quality Issue | G90: DF + SDF
... A103: A8.25 | B103: Sec 6 + Sec 8 | C103: Rule 8 | D103: Incident logs must record any failure/delay in honoring consent withdrawal. | E103: Rule frames DF accountability. | F103: Withdrawal Failure Incident Logging | G103: DF + SDF
A104: Sr. No. (B1 — Lawful Purpose Requirements)
A105: B1.1 | B105: Sec 4(1) | C105: — | D105: DF may process personal data only for a lawful purpose and in accordance with the Act. | E105: — | F105: Lawful Purpose Assessment | G105: DF + SDF
A106: B1.2 | B106: Sec 4(1) | C106: Rule 4 | D106: If processing is based on consent, lawful purpose must be disclosed in notice. | E106: Rule 4 mandates stating purpose clearly in notice. | F106: Purpose Disclosure in Notice | G106: DF + SDF
A107: B1.3 | B107: Sec 4(1) | C107: — | D107: Lawful purpose = any purpose not expressly forbidden by law. | E107: — | F107: Purpose Screening Against Prohibitions | G107: DF + SDF
A108: B1.4 | B108: Sec 4(1) | C108: Rule 4 | D108: Each purpose must be explicit, specific and linked to processing necessity. | E108: Rule enforces purpose-level clarity. | F108: Purpose Definition & Documentation | G108: DF + SDF
A109: B1.5 | B109: Sec 4(1) | C109: — | D109: DF must map each processing activity to a lawful purpose before processing begins. | E109: — | F109: Data Processing–Purpose Mapping | G109: DF + SDF
A110: B1.6 | B110: Sec 4(1) | C110: — | D110: Any new processing purpose requires reassessment and potentially fresh consent/notice. | E110: — | F110: New Purpose Impact Assessment | G110: DF + SDF
A111: B1.7 | B111: Sec 4(1) | C111: Rule 4 | D111: Where multiple purposes exist, DF must separate each purpose in the consent/notice format. | E111: Rule 4 requires multi-purpose transparency. | F111: Multi-purpose Segregation Control | G111: DF + SDF
A112: B1.8 | B112: Sec 4(1) | C112: — | D112: DF must maintain internal purpose registry aligning each processing operation. | E112: — | F112: Purpose Registry Maintenance | G112: DF + SDF
A113: B1.9 | B113: Sec 4(1) | C113: Rule 5 (State) | D113: When DF acts as an instrumentality of State, purpose must align with notified State functions. | E113: Rule 5 defines State processing standards. | F113: State-purpose Alignment Check | G113: DF (State entities)
A114: B1.10 | B114: Sec 5 + Sec 6 | C114: Rule 4 | D114: Notice must always reveal the lawful purpose regardless of the basis (consent or Sec 7). | E114: Rule enforces full transparency. | F114: Lawful Purpose Transparency | G114: DF + SDF
A115: B1.11 | B115: Sec 8(3) | C115: — | D115: Before using data for decisions affecting DP, DF must ensure purpose-consistency. | E115: — | F115: Purpose Consistency Verification | G115: DF + SDF
A116: B1.12 | B116: Sec 8(3) | C116: Rule 4 | D116: Before disclosing data to another DF, ensure the purpose aligns with DP-given scope. | E116: — | F116: Purpose Alignment Before Disclosure | G116: DF + SDF
... A124: B1.20 | B124: Sec 4 + 7 | C124: Rule 4 | D124: DF must map each purpose to one of: consent, legitimate use, State function, emergency, employment, etc. | E124: Rule 4 links notice disclosures to basis. | F124: Purpose-to-Basis Mapping | G124: DF + SDF
A125: Sr. No. (B2.1 — Sec 7(a): Voluntary Data Supply)
A126: B2.1.1 | B126: Sec 7(a) | C126: Rule 4 | D126: DP voluntarily provides data for a specific purpose; DF may process unless DP objects. | E126: Rule requires notice even for voluntary data. | F126: Voluntary Data Processing Enablement | G126: DF + SDF
A127: B2.1.2 | B127: Sec 7(a) | C127: — | D127: DF must stop processing if DP indicates objection after providing data. | E127: — | F127: Voluntary Data Opt-out Control | G127: DF + SDF
A128: B2.1.3 | B128: Sec 7(a) | C128: Rule 4 | D128: DF must still provide notice (data categories, purpose, rights). | E128: Rule 4 enforces mandatory notice components. | F128: Notice for Voluntary Data | G128: DF + SDF
A129: B2.1.4 | B129: Sec 7(a) | C129: — | D129: Voluntary data use cannot exceed the stated purpose. | E129: — | F129: Purpose Limitation for Voluntary Data | G129: DF + SDF
A130: B2.1.5 | B130: Sec 7(a) | C130: Rule 4 | D130: Even though consent isn’t required, transparency obligations remain identical. | E130: Rule supports identical notice requirements. | F130: Transparency Enforcement | G130: DF + SDF
A131: B2.1.6 | B131: Sec 8(3) | C131: — | D131: DF must ensure accuracy when voluntary data affects decisions about the DP. | E131: — | F131: Voluntary Data Accuracy Check | G131: DF + SDF
A132: B2.1.7 | B132: Sec 7(a) | C132: — | D132: Processing voluntary data does not permit covert data collection. | E132: — | F132: No Covert Collection Control | G132: DF + SDF
A133: Sr. No. (B2.2 — Sec 7(b): State Subsidies / Benefits / Services)
A134: B2.2.1 | B134: Sec 7(b)(i) | C134: Rule 5 | D134: State may process personal data to provide prescribed subsidy/benefit/service where DP previously consented. | E134: Rule 5 + Second Schedule list allowed government purposes. | F134: Government Service Eligibility Processing | G134: State DF
A135: B2.2.2 | B135: Sec 7(b)(ii) | C135: Rule 5 | D135: State may process data available in government registers/databases for notified purposes. | E135: Rule 5 defines data access standards. | F135: Processing Using Government Databases | G135: State DF
A136: B2.2.3 | B136: Sec 7(b) | C136: Second Schedule | D136: Only those purposes notified in the Second Schedule are allowed. | E136: Second Schedule enumerates valid purposes. | F136: Notified Purpose Verification | G136: State DF
A137: B2.2.4 | B137: Sec 7(b) | C137: Rule 5 | D137: Standards for processing must follow policy/law for personal data governance. | E137: Rule sets conditions for lawful State processing. | F137: Government Data Governance Compliance | G137: State DF
A138: B2.2.5 | B138: Sec 7(b) | C138: — | D138: DP does not need to provide fresh consent for each benefit. | E138: — | F138: Consent Reuse Policy Control | G138: State DF
...

Sheet Compliance Dashboard
A1: DPDP COMPLIANCE DASHBOARD
A2: Programme Status Overview | 73 Controls | 12 Categories | DPDP Act 2023 & Rules 2025
A4: COMPLIANCE RATE | C4: IMPLEMENTATION RATE | E4: EVIDENCE READINESS | G4: MATURITY SCORE | I4: CRITICAL GAPS
A5: =IFERROR(COUNTIF('Assessment + Implementation'!K:K,"Compliant")/COUNTA('Assessment + Implementation'!A5:A77),0) -> 0.02739726 | C5: =IFERROR((COUNTIF('Assessment + Implementation'!P:P,"Implemented")+COUNTIF('Assessment + Implementation'!P:P,"Verified"))/COUNTA('Assessment + Implementation'!A5:A77),0) -> 0.02739726 | E5: =IFERROR((COUNTIF('Assessment + Implementation'!V:V,"Validated")+COUNTIF('Assessment + Implementation'!V:V,"Audit-Ready"))/COUNTA('Assessment + Implementation'!A5:A77),0) -> 0.02739726 | G5: =IFERROR(SUM('Assessment + Implementation'!L5:L77)/(COUNTA('Assessment + Implementation'!A5:A77)*4),0) -> 0.051369863 | I5: =COUNTIF('Assessment + Implementation'!O:O,"Critical")+COUNTIF('Assessment + Implementation'!D5:D77,"Critical")-COUNTIFS('Assessment + Implementation'!D5:D77,"Critical",'Assessment + Implementation'!K5:K77,"Compliant") -> 11
A6: Compliant / 73 | C6: Implemented + Verified / 73 | E6: Validated + Audit-Ready / 73 | G6: Avg Maturity L0–L4 / Max | I6: Priority Critical not Compliant
A9: ASSESSMENT STATUS DISTRIBUTION | H9: Status | I9: Count
A10: Not Assessed | B10: Compliant | C10: Partially Compliant | D10: Non-Compliant | E10: Not Applicable | F10: Blank | H10: Compliant | I10: =B11 -> 2
A11: =COUNTIF('Assessment + Implementation'!K5:K77,"Not Assessed") -> 0 | B11: =COUNTIF('Assessment + Implementation'!K5:K77,"Compliant") -> 2 | C11: =COUNTIF('Assessment + Implementation'!K5:K77,"Partially Compliant") -> 4 | D11: =COUNTIF('Assessment + Implementation'!K5:K77,"Non-Compliant") -> 3 | E11: =COUNTIF('Assessment + Implementation'!K5:K77,"Not Applicable") -> 1 | F11: =COUNTA('Assessment + Implementation'!A5:A77)-COUNTA('Assessment + Implementation'!K5:K77) -> 63 | H11: Partially Compliant | I11: =C11 -> 4
H12: Non-Compliant | I12: =D11 -> 3
A13: IMPLEMENTATION STATUS DISTRIBUTION | H13: Not Applicable | I13: =E11 -> 1
A14: Not Started | B14: Planning | C14: In Progress | D14: Testing | E14: Implemented | F14: Verified | H14: Not Yet Assessed | I14: =F11 -> 63
A15: =COUNTIF('Assessment + Implementation'!P5:P77,"Not Started") -> 1 | B15: =COUNTIF('Assessment + Implementation'!P5:P77,"Planning") -> 2 | C15: =COUNTIF('Assessment + Implementation'!P5:P77,"In Progress") -> 4 | D15: =COUNTIF('Assessment + Implementation'!P5:P77,"Testing") -> 0 | E15: =COUNTIF('Assessment + Implementation'!P5:P77,"Implemented") -> 1 | F15: =COUNTIF('Assessment + Implementation'!P5:P77,"Verified") -> 1
A18: PRIORITY DISTRIBUTION
A19: Critical | B19: High | C19: Medium | D19: Low | E19: Assessed Risk Gaps
A20: =COUNTIF('Assessment + Implementation'!D5:D77,"Critical") -> 7 | B20: =COUNTIF('Assessment + Implementation'!D5:D77,"High") -> 22 | C20: =COUNTIF('Assessment + Implementation'!D5:D77,"Medium") -> 20 | D20: =COUNTIF('Assessment + Implementation'!D5:D77,"Low") -> 24 | E20: =COUNTIF('Assessment + Implementation'!O5:O77,"Critical")+COUNTIF('Assessment + Implementation'!O5:O77,"High") -> 6
A23: CATEGORY MATURITY OVERVIEW
A24: Category | B24: Controls | C24: Avg Maturity | D24: Compliant | E24: Non-Compliant | F24: Evidence Ready
A25: Consent & Notice | B25: =COUNTIF('Assessment + Implementation'!C5:C77,"Consent & Notice") -> 5 | C25: =IFERROR(AVERAGEIF('Assessment + Implementation'!C5:C77,"Consent & Notice",'Assessment + Implementation'!L5:L77),0) -> 1.5 | D25: =COUNTIFS('Assessment + Implementation'!C5:C77,"Consent & Notice",'Assessment + Implementation'!K5:K77,"Compliant") -> 0 | E25: =COUNTIFS('Assessment + Implementation'!C5:C77,"Consent & Notice",'Assessment + Implementation'!K5:K77,"Non-Compliant") -> 1 | F25: =COUNTIFS('Assessment + Implementation'!C5:C77,"Consent & Notice",'Assessment + Implementation'!V5:V77,"Validated")+COUNTIFS('Assessment + Implementation'!C5:C77,"Consent & Notice",'Assessment + Implementation'!V5:V77,"Audit-Ready") -> 0
A26: Security Safeguards | B26: =COUNTIF('Assessment + Implementation'!C5:C77,"Security Safeguards") -> 7 | C26: =IFERROR(AVERAGEIF('Assessment + Implementation'!C5:C77,"Security Safeguards",'Assessment + Implementation'!L5:L77),0) -> 2 | D26: =COUNTIFS('Assessment + Implementation'!C5:C77,"Security Safeguards",'Assessment + Implementation'!K5:K77,"Compliant") -> 0 | E26: =COUNTIFS('Assessment + Implementation'!C5:C77,"Security Safeguards",'Assessment + Implementation'!K5:K77,"Non-Compliant") -> 0 | F26: =COUNTIFS('Assessment + Implementation'!C5:C77,"Security Safeguards",'Assessment + Implementation'!V5:V77,"Validated")+COUNTIFS('Assessment + Implementation'!C5:C77,"Security Safeguards",'Assessment + Implementation'!V5:V77,"Audit-Ready") -> 0
A27: Breach Notification | B27: =COUNTIF('Assessment + Implementation'!C5:C77,"Breach Notification") -> 7 | C27: =IFERROR(AVERAGEIF('Assessment + Implementation'!C5:C77,"Breach Notification",'Assessment + Implementation'!L5:L77),0) -> 0 | D27: =COUNTIFS('Assessment + Implementation'!C5:C77,"Breach Notification",'Assessment + Implementation'!K5:K77,"Compliant") -> 0 | E27: =COUNTIFS('Assessment + Implementation'!C5:C77,"Breach Notification",'Assessment + Implementation'!K5:K77,"Non-Compliant") -> 1 | F27: =COUNTIFS('Assessment + Implementation'!C5:C77,"Breach Notification",'Assessment + Implementation'!V5:V77,"Validated")+COUNTIFS('Assessment + Implementation'!C5:C77,"Breach Notification",'Assessment + Implementation'!V5:V77,"Audit-Ready") -> 0
A28: Data Principal Rights | B28: =COUNTIF('Assessment + Implementation'!C5:C77,"Data Principal Rights") -> 8 | C28: =IFERROR(AVERAGEIF('Assessment + Implementation'!C5:C77,"Data Principal Rights",'Assessment + Implementation'!L5:L77),0) -> 2 | D28: =COUNTIFS('Assessment + Implementation'!C5:C77,"Data Principal Rights",'Assessment + Implementation'!K5:K77,"Compliant") -> 0 | E28: =COUNTIFS('Assessment + Implementation'!C5:C77,"Data Principal Rights",'Assessment + Implementation'!K5:K77,"Non-Compliant") -> 0 | F28: =COUNTIFS('Assessment + Implementation'!C5:C77,"Data Principal Rights",'Assessment + Implementation'!V5:V77,"Validated")+COUNTIFS('Assessment + Implementation'!C5:C77,"Data Principal Rights",'Assessment + Implementation'!V5:V77,"Audit-Ready") -> 0
A29: Consent Manager | B29: =COUNTIF('Assessment + Implementation'!C5:C77,"Consent Manager") -> 6 | C29: =IFERROR(AVERAGEIF('Assessment + Implementation'!C5:C77,"Consent Manager",'Assessment + Implementation'!L5:L77),0) -> 0 | D29: =COUNTIFS('Assessment + Implementation'!C5:C77,"Consent Manager",'Assessment + Implementation'!K5:K77,"Compliant") -> 0 | E29: =COUNTIFS('Assessment + Implementation'!C5:C77,"Consent Manager",'Assessment + Implementation'!K5:K77,"Non-Compliant") -> 0 | F29: =COUNTIFS('Assessment + Implementation'!C5:C77,"Consent Manager",'Assessment + Implementation'!V5:V77,"Validated")+COUNTIFS('Assessment + Implementation'!C5:C77,"Consent Manager",'Assessment + Implementation'!V5:V77,"Audit-Ready") -> 0
A30: Retention & Erasure | B30: =COUNTIF('Assessment + Implementation'!C5:C77,"Retention & Erasure") -> 5 | C30: =IFERROR(AVERAGEIF('Assessment + Implementation'!C5:C77,"Retention & Erasure",'Assessment + Implementation'!L5:L77),0) -> 3 | D30: =COUNTIFS('Assessment + Implementation'!C5:C77,"Retention & Erasure",'Assessment + Implementation'!K5:K77,"Compliant") -> 1 | E30: =COUNTIFS('Assessment + Implementation'!C5:C77,"Retention & Erasure",'Assessment + Implementation'!K5:K77,"Non-Compliant") -> 0 | F30: =COUNTIFS('Assessment + Implementation'!C5:C77,"Retention & Erasure",'Assessment + Implementation'!V5:V77,"Validated")+COUNTIFS('Assessment + Implementation'!C5:C77,"Retention & Erasure",'Assessment + Implementation'!V5:V77,"Audit-Ready") -> 1
A31: Children & Exemptions | B31: =COUNTIF('Assessment + Implementation'!C5:C77,"Children & Exemptions") -> 16 | C31: =IFERROR(AVERAGEIF('Assessment + Implementation'!C5:C77,"Children & Exemptions",'Assessment + Implementation'!L5:L77),0) -> 0 | D31: =COUNTIFS('Assessment + Implementation'!C5:C77,"Children & Exemptions",'Assessment + Implementation'!K5:K77,"Compliant") -> 0 | E31: =COUNTIFS('Assessment + Implementation'!C5:C77,"Children & Exemptions",'Assessment + Implementation'!K5:K77,"Non-Compliant") -> 1 | F31: =COUNTIFS('Assessment + Implementation'!C5:C77,"Children & Exemptions",'Assessment + Implementation'!V5:V77,"Validated")+COUNTIFS('Assessment + Implementation'!C5:C77,"Children & Exemptions",'Assessment + Implementation'!V5:V77,"Audit-Ready") -> 0
A32: SDF Obligations | B32: =COUNTIF('Assessment + Implementation'!C5:C77,"SDF Obligations") -> 7 | C32: =IFERROR(AVERAGEIF('Assessment + Implementation'!C5:C77,"SDF Obligations",'Assessment + Implementation'!L5:L77),0) -> 0 | D32: =COUNTIFS('Assessment + Implementation'!C5:C77,"SDF Obligations",'Assessment + Implementation'!K5:K77,"Compliant") -> 0 | E32: =COUNTIFS('Assessment + Implementation'!C5:C77,"SDF Obligations",'Assessment + Implementation'!K5:K77,"Non-Compliant") -> 0 | F32: =COUNTIFS('Assessment + Implementation'!C5:C77,"SDF Obligations",'Assessment + Implementation'!V5:V77,"Validated")+COUNTIFS('Assessment + Implementation'!C5:C77,"SDF Obligations",'Assessment + Implementation'!V5:V77,"Audit-Ready") -> 0
A33: Cross-Border Transfer | B33: =COUNTIF('Assessment + Implementation'!C5:C77,"Cross-Border Transfer") -> 2 | C33: =IFERROR(AVERAGEIF('Assessment + Implementation'!C5:C77,"Cross-Border Transfer",'Assessment + Implementation'!L5:L77),0) -> 1 | D33: =COUNTIFS('Assessment + Implementation'!C5:C77,"Cross-Border Transfer",'Assessment + Implementation'!K5:K77,"Compliant") -> 0 | E33: =COUNTIFS('Assessment + Implementation'!C5:C77,"Cross-Border Transfer",'Assessment + Implementation'!K5:K77,"Non-Compliant") -> 0 | F33: =COUNTIFS('Assessment + Implementation'!C5:C77,"Cross-Border Transfer",'Assessment + Implementation'!V5:V77,"Validated")+COUNTIFS('Assessment + Implementation'!C5:C77,"Cross-Border Transfer",'Assessment + Implementation'!V5:V77,"Audit-Ready") -> 0
A34: Research & Archiving | B34: =COUNTIF('Assessment + Implementation'!C5:C77,"Research & Archiving") -> 7 | C34: =IFERROR(AVERAGEIF('Assessment + Implementation'!C5:C77,"Research & Archiving",'Assessment + Implementation'!L5:L77),0) -> 0 | D34: =COUNTIFS('Assessment + Implementation'!C5:C77,"Research & Archiving",'Assessment + Implementation'!K5:K77,"Compliant") -> 0 | E34: =COUNTIFS('Assessment + Implementation'!C5:C77,"Research & Archiving",'Assessment + Implementation'!K5:K77,"Non-Compliant") -> 0 | F34: =COUNTIFS('Assessment + Implementation'!C5:C77,"Research & Archiving",'Assessment + Implementation'!V5:V77,"Validated")+COUNTIFS('Assessment + Implementation'!C5:C77,"Research & Archiving",'Assessment + Implementation'!V5:V77,"Audit-Ready") -> 0
A35: Contact & Publication | B35: =COUNTIF('Assessment + Implementation'!C5:C77,"Contact & Publication") -> 2 | C35: =IFERROR(AVERAGEIF('Assessment + Implementation'!C5:C77,"Contact & Publication",'Assessment + Implementation'!L5:L77),0) -> 4 | D35: =COUNTIFS('Assessment + Implementation'!C5:C77,"Contact & Publication",'Assessment + Implementation'!K5:K77,"Compliant") -> 1 | E35: =COUNTIFS('Assessment + Implementation'!C5:C77,"Contact & Publication",'Assessment + Implementation'!K5:K77,"Non-Compliant") -> 0 | F35: =COUNTIFS('Assessment + Implementation'!C5:C77,"Contact & Publication",'Assessment + Implementation'!V5:V77,"Validated")+COUNTIFS('Assessment + Implementation'!C5:C77,"Contact & Publication",'Assessment + Implementation'!V5:V77,"Audit-Ready") -> 1
A36: Govt. Information Requests | B36: =COUNTIF('Assessment + Implementation'!C5:C77,"Govt. Information Requests") -> 1 | C36: =IFERROR(AVERAGEIF('Assessment + Implementation'!C5:C77,"Govt. Information Requests",'Assessment + Implementation'!L5:L77),0) -> 0 | D36: =COUNTIFS('Assessment + Implementation'!C5:C77,"Govt. Information Requests",'Assessment + Implementation'!K5:K77,"Compliant") -> 0 | E36: =COUNTIFS('Assessment + Implementation'!C5:C77,"Govt. Information Requests",'Assessment + Implementation'!K5:K77,"Non-Compliant") -> 0 | F36: =COUNTIFS('Assessment + Implementation'!C5:C77,"Govt. Information Requests",'Assessment + Implementation'!V5:V77,"Validated")+COUNTIFS('Assessment + Implementation'!C5:C77,"Govt. Information Requests",'Assessment + Implementation'!V5:V77,"Audit-Ready") -> 0

Sheet Framework Guide
B1: DPDP COMPLIANCE FRAMEWORK — USER GUIDE
B3: FRAMEWORK ARCHITECTURE
B4: Express Evaluation | C4: Complete this sheet FIRST. It determines your entity classification (DF/SDF/CM), applicable control domains, and sector-specific obligations. The auto-computed Applicability Result column directs you to relevant controls in the Assessment + Implementation tracker.
B5: RACI Matrix | C5: Maps every compliance control to functional and business unit-level responsibilities using R (Responsible), A (Accountable), C (Consulted), I (Informed). Central functions (DPO, CISO, Legal, IT, HR, Product, Procurement, Ops) and BU-level roles (BU Head, BU Privacy Champion, BU IT Lead) are both addressed. Customise RACI assignments to your org structure.
B6: Assessment + Implementation | C6: The single master compliance tracker. Control Identification (cols A–J): Sr. No., Control ID, Category (12 domains), Priority (Critical/High/Medium/Low), DPDP Section, Max Penalty, Reference, Role, Compliance Header, and Compliance Measures. Assessment Area (cols K–O): Assessment Status, Maturity Level (L0–L4), Gap Identified, Gap Description, Risk Rating. Implementation Area (cols P–U): Impl. Status, Accountable Owner, Target Date, Action Plan, Budget Est., % Complete. Governance & Evidence (cols V–Y): Evidence Status, Evidence Artefact/Location, Last Review Date, Reviewer Comments. Built-in Assessment Summary (rows 79–101) auto-calculates readiness scores. All Dashboard KPIs pull live from this sheet.
B7: Granular Controls | C7: 340 discrete control items decomposed from the Act and Rules. Enhanced with Assessment Status, Maturity Level, Implementation Status, Ownership, Risk Rating, and Evidence Status columns for operational tracking. Use this for engineering and process implementation.
B9: MATURITY MODEL
B10: L0 — Absent | C10: No documented or implemented control exists for this requirement.
B11: L1 — Documented | C11: Policy, procedure, or standard operating procedure exists but may not be consistently implemented.
B12: L2 — Implemented | C12: Control is deployed and operational across relevant systems and processes.
B13: L3 — Monitored | C13: Control effectiveness is periodically measured, reported, and reviewed.
B14: L4 — Optimised | C14: Control is continuously improved based on metrics, incidents, and regulatory developments.
B16: IMPLEMENTATION LIFECYCLE
B17: Not Started | C17: Control has not entered implementation planning.
B18: Planning | C18: Requirements gathered, owner assigned, approach designed.
B19: In Progress | C19: Active development, configuration, or deployment underway.
B20: Testing | C20: Control implemented and undergoing UAT, validation, or pilot.
B21: Implemented | C21: Control deployed in production across applicable scope.
B22: Verified | C22: Independent verification (audit, review, or testing) confirms control effectiveness.
B24: RACI DEFINITIONS
B25: R — Responsible | C25: Executes the work. The function or individual who performs the control activity, builds the system, drafts the policy, or conducts the assessment.
B26: A — Accountable | C26: Owns the outcome. The single function that is ultimately answerable for the control's compliance. Only one 'A' per control row is ideal.
B27: C — Consulted | C27: Provides input. Functions whose expertise is required before or during control implementation (two-way communication).
B28: I — Informed | C28: Kept updated. Functions that need to be notified of progress, decisions, or outcomes (one-way communication).
B30: BUSINESS UNIT BIFURCATION
B31: When to Activate | C31: If your Express Evaluation question D6 = Yes (multiple BUs processing PD independently), the BU columns in the RACI Matrix become operative. Each BU should have a named Privacy Champion and IT Lead.
B32: BU Head | C32: Accountable for BU-level compliance posture. Ensures BU-specific processing activities are mapped and controls are implemented.
B33: BU Privacy Champion | C33: BU-embedded privacy liaison. Responsible for BU-level consent operations, rights handling, and coordination with central DPO.
B34: BU IT Lead | C34: Responsible for BU-level technical controls: encryption, access management, logging, and system configurations.
B36: RISK RATING GUIDE
B37: Critical | C37: Penalty exposure up to INR 250 Cr; direct regulatory enforcement risk; breach-related obligations; child data non-compliance.
B38: High | C38: Significant compliance gap with operational or reputational impact; rights denial; security inadequacy.
B39: Medium | C39: Moderate gap requiring remediation within defined timeline; partial implementation that needs enhancement.
B40: Low | C40: Minor gap or advisory control; low enforcement probability; optimisation-level improvement.
B42: DEFINITIONS / GLOSSARY | C42: Description
B43: Statutory Reference | C43: The following definitions are drawn from Section 2 of the Digital Personal Data Protection Act, 2023 ("the Act") and Rule 2 of the Digital Personal Data Protection Rules, 2025 ("the Rules"). Terms not defined in the Rules carry the meanings assigned to them in the Act [Rule 2(2)]. Users should refer to the full text of Sec. 2 and Rule 2 for complete statutory language.
B44: Appellate Tribunal [Sec. 2(a)] | C44: Means the Telecom Disputes Settlement and Appellate Tribunal (TDSAT) established under Section 14 of the Telecom Regulatory Authority of India Act, 1997. Hears appeals against orders of the Data Protection Board of India.
B45: Board [Sec. 2(c)] | C45: Means the Data Protection Board of India established by the Central Government under Section 18 of the Act. The Board adjudicates complaints, inquires into breaches, and imposes monetary penalties.
B46: Certain Legitimate Uses [Sec. 2(d)] | C46: Means the uses referred to in Section 7 of the Act, under which personal data may be processed without the Data Principal's consent (e.g., voluntary provision of data, State functions, compliance with law, medical emergencies, employment purposes).
B47: Child [Sec. 2(f)] | C47: Means an individual who has not completed the age of eighteen years. Verifiable parental or lawful guardian consent is required before processing a child's personal data (Sec. 9, Rules 10 & 12).
B48: Consent [Sec. 6] | C48: Must be free, specific, informed, unconditional, and unambiguous with a clear affirmative action by the Data Principal. Consent shall be limited to such personal data as is necessary for the specified purpose. Any part of consent that infringes the Act or Rules is invalid to the extent of such infringement.
B49: Consent Manager [Sec. 2(g)] | C49: Means a person registered with the Board, who acts as a single point of contact to enable a Data Principal to give, manage, review and withdraw her consent through an accessible, transparent and interoperable platform (Rule 4 prescribes registration, eligibility and obligations).
... B61: Specified Purpose [Sec. 2(za)] | C61: Means the purpose mentioned in the notice given by the Data Fiduciary to the Data Principal in accordance with the provisions of the Act and the Rules made thereunder. Data must be erased once the specified purpose is no longer served (Sec. 8(7), Rule 8).
B63: RULE 2 DEFINITIONS (DPDP Rules, 2025)
B64: Act [Rule 2(1)(a)] | C64: Means the Digital Personal Data Protection Act, 2023 (22 of 2023). All references to "the Act" in the Rules refer to this statute.
B65: Techno-Legal Measures [Rule 2(1)(b)] | C65: Means as referred to under Rules 20 and 22. These are the technical and procedural mechanisms the Data Protection Board and the Appellate Tribunal must adopt to function as digital offices (e.g., online filing, digital hearings, electronic case management).
B66: User Account [Rule 2(1)(c)] | C66: Means the online account registered by the Data Principal with the Data Fiduciary, and includes any profiles, pages, handles, email address, mobile number and other similar presences by means of which such Data Principal is able to access the services of such Data Fiduciary.
B67: Verifiable Consent [Rule 2(1)(d)] | C67: Means a consent as specified in Rule 10 (processing of personal data of a child) or Rule 11 (processing of personal data of a person with disability). Requires the Data Fiduciary to adopt appropriate technical and organisational measures to verify identity and age of the parent or lawful guardian.
B68: Residual Definitions [Rule 2(2)] | C68: The words and expressions used in the Rules and not defined therein, but defined in the Act, shall have the same meanings as respectively assigned to them in the Act. This ensures consistency between the Act and the Rules.
B70: ABBREVIATIONS USED IN THIS FRAMEWORK
B71: DF / SDF / CM / DP / DPO | C71: Data Fiduciary [Sec. 2(i)] / Significant Data Fiduciary [Sec. 2(z)] / Consent Manager [Sec. 2(g)] / Data Principal [Sec. 2(j)] / Data Protection Officer [Sec. 2(l)].
B72: DPIA / PD / BU | C72: Data Protection Impact Assessment [Sec. 10(2)(c)(i)] / Personal Data [Sec. 2(t)] / Business Unit (framework-specific designation for multi-BU organisations).
B73: The Act / The Rules / The Board | C73: The Digital Personal Data Protection Act, 2023 (No. 22 of 2023) / The Digital Personal Data Protection Rules, 2025 (G.S.R. 846(E), dated 13 November 2025) / The Data Protection Board of India [Sec. 2(c), Sec. 18].

Sheet Claude Log
A1: Turn # | B1: Date | C1: User Request | D1: Action Taken | E1: Details | F1: Outcome
A2: 1 | B2: 46082 | C2: Integrate a 76-control DPDP compliance assessment matrix (with Control IDs, categories, priorities, maturity scores, evidence tracking, gap notes, DPDP sections, max penalties, and assessment summary) into the existing framework. | D2: Created new 'DPDP Assessment' sheet with all 76 controls and live summary formulas. | E2: Built sheet with: 76 controls in rows 4-79 with columns (#, Control ID, Category, Priority, Control Name, Key Assessment Question, Maturity 0-4, Evidence?, Gap/Notes, DPDP Section, Max Penalty). Assessment Summary in rows 81-103 with SUMPRODUCT/COUNTIF/AVERAGEIF formulas for Overall Readiness (by priority tier) and Category Breakdown (11 categories). Added data validation (0-4 dropdown for maturity, Yes/No for evidence), conditional formatting (priority-based row colors: red=Critical, orange=High, yellow=Medium, green=Low), borders, freeze panes on row 3. Pre-populated maturity scores: GOV-001=2, GOV-002=4, GOV-003=1, all others=0. All summary formulas verified: Overall 7/304 (2.3%), Critical 7/56 (12.5%). | F2: DPDP Assessment sheet created as 2nd tab. All 76 controls loaded, summary auto-calculates. Ready for maturity scoring by assessment teams.
A3: 2 | B3: 46082 | C3: User provided a detailed prompt template for creating an 'EP - Self Assessment' sheet with specific formatting (Aptos Narrow font, maturity color scale, priority badges, assessment summary). Asked to build it using this workbook's existing data from Assessment + Implementation sheet. | D3: Created 'EP - Self Assessment' sheet with 73 controls sourced from the Assessment + Implementation sheet (74 items, minus missing Sr. 72). Applied all prompt specifications. | E3: Built with: (1) 3 merged header rows (title, subtitle, maturity scale legend) in dark navy/light gray; (2) 73 data rows (A5:K77) using Control IDs from RACI Matrix (CN-01..GR-01), 12 categories, priority-coded cells (red/orange/amber/green badges), maturity 0-4 with conditional color scale (dark orange→light yellow), Evidence Yes/No dropdown; (3) Overall Readiness summary (rows 81-86) with SUMPRODUCT formulas by priority tier; (4) Category Breakdown (rows 89-101) with AVERAGEIF/COUNTIF/COUNTIFS for 12 categories. Freeze panes at C5 (row 4 + col B frozen). Aptos Narrow font throughout. Alternating row colors #F5F7FA/#FFFFFF. | F3: EP - Self Assessment sheet created as 3rd tab. 73 controls with full formatting per prompt spec. All summary formulas verified. Ready for maturity scoring.
A4: 3 | B4: 46082 | C4: User identified overlap between 3 sheets doing the same thing (DPDP Assessment, EP - Self Assessment, Assessment + Implementation). Asked for consolidation recommendations. | D4: Audited all sheets, identified triple-assessment overlap, recommended and executed consolidation: enhanced Assessment + Implementation as single master, hid redundant sheets. | E4: Audit found: A+I (73 items, full assessment+implementation+evidence), DPDP Assessment (76 controls, maturity only), EP (73 controls, maturity only) all assessed the same DPDP controls differently. Resolution: (1) Inserted 5 new columns into A+I (Control ID, Category, Priority, DPDP Section, Max Penalty) at cols B-F using RACI Matrix control ID scheme (CN-01, SS-01 etc.); (2) Added priority conditional formatting (red/orange/amber/green); (3) Built Assessment Summary section (rows 79-101) with Overall Readiness by priority tier + Category Breakdown (12 categories) using SUMPRODUCT/AVERAGEIF referencing Maturity Level col L; (4) Updated freeze panes to A-E frozen; (5) Hid DPDP Assessment sheet; EP was already hidden. Dashboard still needs wiring to pull from A+I. | F4: Assessment + Implementation is now the single master with 25 columns (A-Y). Both DPDP Assessment and EP - Self Assessment are hidden. Control IDs match RACI Matrix. Summary auto-calculates. Dashboard connection still pending.
A5: 4 | B5: 46082 | C5: User requested alignment of ReadMe, Framework Guide, and Compliance Dashboard with the enhanced A+I sheet. Workbook is being prepared as a senior-level work sample — needs to be crisp and polished. | D5: Rebuilt Compliance Dashboard from scratch, updated ReadMe column references, updated Framework Guide A+I description. | E5: Dashboard: (1) 5 KPI scorecards at top (Compliance Rate %, Implementation Rate %, Evidence Readiness %, Maturity Score %, Critical Gaps) with large 22pt numbers; (2) Assessment Status Distribution (6 statuses incl. Blank count); (3) Implementation Status Distribution (6 lifecycle stages); (4) Priority Distribution with color-coded badges; (5) Category Maturity Overview with 12 categories showing Controls, Avg Maturity, Compliant, Non-Compliant, Evidence Ready. All formulas reference A+I cols K (Assessment Status), L (Maturity), O (Risk Rating), P (Impl Status), V (Evidence Status), C (Category), D (Priority). ReadMe: Updated Step 3 refs F–J → K–O, Step 4 refs K–P → P–U, Step 6 refs Q–T → V–Y. Updated Scope & Coverage and architecture description for A+I. Framework Guide: Rewrote A+I entry with all 25 columns documented. | F5: All 3 sheets aligned. Dashboard is fully live with formulas. ReadMe column references corrected. Framework Guide reflects enhanced A+I structure. All currently show baseline state (73 blank, 0 assessed). Ready for senior sharing.
A6: 5 | B6: 46082 | C6: User asked if workbook is ready to share as a C-suite work sample. | D6: Final review and polish pass: hid Claude Log, reordered all tabs for executive flow. | E6: Issues found & fixed: (1) Claude Log was visible as first tab — hidden. (2) Tab order was wrong (Framework Guide before Express Eval, Dashboard last) — reordered to: ReadMe → Express Evaluation → RACI Matrix → Assessment + Implementation → Granular Controls → Compliance Dashboard → Framework Guide. (3) All formulas verified: Dashboard KPIs correct (7 Critical Gaps, 73 Blank, category counts sum to 73, priority 7+22+20+24=73). All cross-sheet references intact. ReadMe column refs updated. Framework Guide description current. | F6: Workbook is C-suite ready. 7 visible tabs in logical flow. 3 sheets hidden (Claude Log, EP - Self Assessment, DPDP Assessment). All formulas live. Clean baseline state awaiting assessment input.
A7: 6 | B7: 46082 | C7: User asked for honest C-suite evaluation. Followed up requesting both sample data and Dashboard charts before sharing. | D7: Provided critical C-suite lens review. Filled 10 controls with realistic sample data across 8 categories. Added 2 charts to Dashboard (doughnut + bar). | E7: Sample data: 10 controls filled with realistic scenario (mid-size Indian tech co, DF not SDF). Mix: 2 Compliant (RE-04, CP-01), 4 Partially Compliant (CN-01, SS-01, DPR-01, CBT-01), 3 Non-Compliant (CN-03, BN-01, CD-01), 1 N/A (SDF-01). Each has maturity L0-L4, gap descriptions, owners, target dates, action plans, budgets, % complete, evidence status. Dashboard now shows live: 2.7% compliance, 5.1% maturity, 11 critical gaps. Charts: Assessment Status doughnut at H4, Category Maturity bar chart at H19. Helper data in H9:I14. | F7: Workbook now demonstrates both the framework structure AND its operational use. Dashboard has real numbers and visual charts. Ready for C-suite sharing.
A8: 7 | B8: 46082 | C8: User requested insertion of a Definitions/Glossary section in Framework Guide, referencing Sec 2 of the DPDP Act, 2023 and Rule 2 of the DPDP Rules, 2025 with correct statutory verbiage. | D8: Created comprehensive Definitions/Glossary section in Framework Guide (rows 42-73) with three sub-sections: (1) Sec 2 Act definitions, (2) Rule 2 Rules definitions, (3) Abbreviations. | E8: Added 18 key definitions from Sec 2 of the Act (Appellate Tribunal, Board, Certain Legitimate Uses, Child, Consent, Consent Manager, Data, Data Fiduciary, Data Principal, Data Processor, DPO, Digital Personal Data, Person, Personal Data, Personal Data Breach, Processing, SDF, Specified Purpose) and 5 entries from Rule 2 of the Rules (Act, Techno-Legal Measures, User Account, Verifiable Consent, Residual Definitions). Added abbreviations decoder (DF/SDF/CM/DP/DPO, DPIA/PD/BU, The Act/Rules/Board). All definitions verified against official gazette text (indiankanoon.org, dpdpact2023.com, dpdpa.com). Matching formatting: navy headers, alternating row colors #EBF5FB/#FFFFFF, Arial 9pt, thin #BDC3C7 borders. | F8: Definitions/Glossary now live in Framework Guide rows 42-73. Three sub-sections with correct statutory clause references. Formatting matches existing guide style.

Sheet EP - Self Assessment
A1: DPDP ACT 2023 — EXPRESS PACK SELF-ASSESSMENT TOOLKIT
A2: Universal Edition | 73 Controls | 12 Categories | Maturity Scale 0–4 | Score your organisation's DPDP readiness
A3: MATURITY SCALE: 0 = Not Started | 1 = Ad-hoc / Informal | 2 = Defined & Documented | 3 = Managed & Monitored | 4 = Optimised & Continuous
A4: # | B4: Control ID | C4: Category | D4: Priority | E4: Control Name | F4: Key Assessment Question | G4: Maturity (0-4) | H4: Evidence? | I4: Gap / Notes | J4: DPDP Section | K4: Max Penalty
A5: 1 | B5: CN-01 | C5: Consent & Notice | D5: Critical | E5: Identify Legal Basis for Processing (Consent or Legitimate Use) | F5: Has the organisation documented a lawful basis (consent or legitimate use) for each processing activity? | G5: 0 | H5: No | J5: Sec. 4, 5, 6, Rule 3 | K5: ₹50 Cr
A6: 2 | B6: CN-02 | C6: Consent & Notice | D6: High | E6: Display & Serve Mandatory Notice (Standalone Notice) | F6: Are standalone, plain-language privacy notices served at or before every data collection point? | G6: 0 | H6: No | J6: Sec. 4, 5, 6, Rule 3 | K6: ₹50 Cr
A7: 3 | B7: CN-03 | C7: Consent & Notice | D7: Critical | E7: Obtain Valid Consent | F7: Are consent mechanisms compliant — free, specific, informed, unambiguous, and affirmative? | G7: 0 | H7: No | J7: Sec. 4, 5, 6, Rule 3 | K7: ₹50 Cr
A8: 4 | B8: CN-04 | C8: Consent & Notice | D8: High | E8: Enable Consent Withdrawal & Stop Processing After Withdrawal | F8: Is a consent withdrawal mechanism available that is as easy as giving consent, with processing stopped upon withdrawal? | G8: 0 | H8: No | J8: Sec. 4, 5, 6, Rule 3 | K8: ₹50 Cr
A9: 5 | B9: CN-05 | C9: Consent & Notice | D9: High | E9: Maintain Notice Content & Presentation Standard | F9: Are notice templates version-controlled, published separately from T&Cs, and retained with historical logs? | G9: 0 | H9: No | J9: Sec. 4, 5, 6, Rule 3 | K9: ₹50 Cr
A10: 6 | B10: CM-01 | C10: Consent Manager | D10: Medium | E10: Eligibility & Application Filing | F10: Has the organisation prepared evidence for all Part A eligibility criteria for Consent Manager registration? | G10: 0 | H10: No | J10: Sec. 6(9), Rule 4 | K10: ₹50 Cr
A11: 7 | B11: CM-02 | C11: Consent Manager | D11: Medium | E11: Board Evaluation & Decision | F11: Is verifiable compliance documentation maintained and aligned with actual operations for Board evaluation? | G11: 0 | H11: No | J11: Sec. 6(9), Rule 4 | K11: ₹50 Cr
A12: 8 | B12: CM-03 | C12: Consent Manager | D12: High | E12: Registered Consent Manager Operating Obligations | F12: Are secure, transparent consent lifecycle handling and audit-ready operational logs maintained? | G12: 0 | H12: No | J12: Sec. 6(9), Rule 4 | K12: ₹50 Cr
A13: 9 | B13: CM-04 | C13: Consent Manager | D13: Medium | E13: Non-Adherence & Corrective Action | F13: Is a continuous compliance assurance framework with quarterly internal control audits operational? | G13: 0 | H13: No | J13: Sec. 6(9), Rule 4 | K13: ₹50 Cr
A14: 10 | B14: CM-05 | C14: Consent Manager | D14: Low | E14: Suspension or Cancellation Power | F14: Are business continuity, handover, and exit playbooks in place for consent record management? | G14: 0 | H14: No | J14: Sec. 6(9), Rule 4 | K14: ₹50 Cr
A15: 11 | B15: CM-06 | C15: Consent Manager | D15: Low | E15: Mandatory Information Disclosure to Board | F15: Is a central evidence and document repository with version-controlled policies and Board-response SOP maintained? | G15: 0 | H15: No | J15: Sec. 6(9), Rule 4 | K15: ₹50 Cr
A16: 12 | B16: SS-01 | C16: Security Safeguards | D16: Critical | E16: Implement Reasonable Security Safeguards | F16: Are ALL Rule 6 safeguards implemented: encryption, access controls, logging, backup, and monitoring? | G16: 0 | H16: No | J16: Sec. 8(5), Rule 6 | K16: ₹250 Cr
... A77: 73 | B77: GR-01 | C77: Govt. Information Requests | D77: Critical | E77: Furnishing Information to Central Government | F77: Is a Regulatory Request Handling SOP maintained with authority verification and secure, logged transmission? | G77: 0 | H77: No | J77: Sec. 36, Rule 23 | K77: ₹250 Cr
A79: ASSESSMENT SUMMARY
B81: OVERALL READINESS | G81: Score | H81: Max | I81: % Complete
B82: Overall Maturity Score | G82: =SUM(G5:G77) -> 0 | H82: =COUNTA(A5:A77)*4 -> 292 | I82: =IF(H82=0,0,G82/H82) -> 0
B83: Critical Controls Score | G83: {=SUMPRODUCT((D5:D77="Critical")*G5:G77)} -> 0 | H83: =COUNTIF(D5:D77,"Critical")*4 -> 28 | I83: =IF(H83=0,0,G83/H83) -> 0
B84: High Controls Score | G84: {=SUMPRODUCT((D5:D77="High")*G5:G77)} -> 0 | H84: =COUNTIF(D5:D77,"High")*4 -> 88 | I84: =IF(H84=0,0,G84/H84) -> 0
B85: Medium Controls Score | G85: {=SUMPRODUCT((D5:D77="Medium")*G5:G77)} -> 0 | H85: =COUNTIF(D5:D77,"Medium")*4 -> 80 | I85: =IF(H85=0,0,G85/H85) -> 0
B86: Low Controls Score | G86: {=SUMPRODUCT((D5:D77="Low")*G5:G77)} -> 0 | H86: =COUNTIF(D5:D77,"Low")*4 -> 96 | I86: =IF(H86=0,0,G86/H86) -> 0
B89: CATEGORY BREAKDOWN | G89: Avg Maturity | H89: Controls | I89: Evidence Ready
B90: Consent & Notice | G90: =IFERROR(AVERAGEIF(C5:C77,"Consent & Notice",G5:G77),0) -> 0 | H90: =COUNTIF(C5:C77,"Consent & Notice") -> 5 | I90: =COUNTIFS(C5:C77,"Consent & Notice",H5:H77,"Yes") -> 0
B91: Consent Manager | G91: =IFERROR(AVERAGEIF(C5:C77,"Consent Manager",G5:G77),0) -> 0 | H91: =COUNTIF(C5:C77,"Consent Manager") -> 6 | I91: =COUNTIFS(C5:C77,"Consent Manager",H5:H77,"Yes") -> 0
B92: Security Safeguards | G92: =IFERROR(AVERAGEIF(C5:C77,"Security Safeguards",G5:G77),0) -> 0 | H92: =COUNTIF(C5:C77,"Security Safeguards") -> 7 | I92: =COUNTIFS(C5:C77,"Security Safeguards",H5:H77,"Yes") -> 0
B93: Breach Notification | G93: =IFERROR(AVERAGEIF(C5:C77,"Breach Notification",G5:G77),0) -> 0 | H93: =COUNTIF(C5:C77,"Breach Notification") -> 7 | I93: =COUNTIFS(C5:C77,"Breach Notification",H5:H77,"Yes") -> 0
B94: Retention & Erasure | G94: =IFERROR(AVERAGEIF(C5:C77,"Retention & Erasure",G5:G77),0) -> 0 | H94: =COUNTIF(C5:C77,"Retention & Erasure") -> 5 | I94: =COUNTIFS(C5:C77,"Retention & Erasure",H5:H77,"Yes") -> 0
B95: Children & Exemptions | G95: =IFERROR(AVERAGEIF(C5:C77,"Children & Exemptions",G5:G77),0) -> 0 | H95: =COUNTIF(C5:C77,"Children & Exemptions") -> 16 | I95: =COUNTIFS(C5:C77,"Children & Exemptions",H5:H77,"Yes") -> 0
B96: SDF Obligations | G96: =IFERROR(AVERAGEIF(C5:C77,"SDF Obligations",G5:G77),0) -> 0 | H96: =COUNTIF(C5:C77,"SDF Obligations") -> 7 | I96: =COUNTIFS(C5:C77,"SDF Obligations",H5:H77,"Yes") -> 0
B97: Data Principal Rights | G97: =IFERROR(AVERAGEIF(C5:C77,"Data Principal Rights",G5:G77),0) -> 0 | H97: =COUNTIF(C5:C77,"Data Principal Rights") -> 8 | I97: =COUNTIFS(C5:C77,"Data Principal Rights",H5:H77,"Yes") -> 0
B98: Cross-Border Transfer | G98: =IFERROR(AVERAGEIF(C5:C77,"Cross-Border Transfer",G5:G77),0) -> 0 | H98: =COUNTIF(C5:C77,"Cross-Border Transfer") -> 2 | I98: =COUNTIFS(C5:C77,"Cross-Border Transfer",H5:H77,"Yes") -> 0
B99: Research & Archiving | G99: =IFERROR(AVERAGEIF(C5:C77,"Research & Archiving",G5:G77),0) -> 0 | H99: =COUNTIF(C5:C77,"Research & Archiving") -> 7 | I99: =COUNTIFS(C5:C77,"Research & Archiving",H5:H77,"Yes") -> 0
B100: Contact & Publication | G100: =IFERROR(AVERAGEIF(C5:C77,"Contact & Publication",G5:G77),0) -> 0 | H100: =COUNTIF(C5:C77,"Contact & Publication") -> 2 | I100: =COUNTIFS(C5:C77,"Contact & Publication",H5:H77,"Yes") -> 0
B101: Govt. Information Requests | G101: =IFERROR(AVERAGEIF(C5:C77,"Govt. Information Requests",G5:G77),0) -> 0 | H101: =COUNTIF(C5:C77,"Govt. Information Requests") -> 1 | I101: =COUNTIFS(C5:C77,"Govt. Information Requests",H5:H77,"Yes") -> 0

Sheet DPDP Assessment
A1: DPDP COMPLIANCE FRAMEWORK — CONTROL ASSESSMENT MATRIX
A2: Purpose: Assess maturity (0–4) for each control, document evidence status and gaps. Summary scores auto-calculate below. Aligned to DPDP Act 2023 & Rules 2025.
A3: # | B3: Control ID | C3: Category | D3: Priority | E3: Control Name | F3: Key Assessment Question | G3: Maturity (0-4) | H3: Evidence? | I3: Gap / Notes | J3: DPDP Section | K3: Max Penalty
A4: 1 | B4: GOV-001 | C4: Governance & Accountability | D4: Critical | E4: Applicability of the law as Controller | F4: Has the organisation determined and documented its Controller/Data Fiduciary role for each processing activity? | G4: 2 | H4: No | J4: Sec. 2(i), 3, 4 | K4: ₹50 Cr
A5: 2 | B5: GOV-002 | C5: Governance & Accountability | D5: Critical | E5: Applicability of the law as Processor | F5: Are Data Processing Agreements in place with all controllers, incorporating Rule 6 security requirements? | G5: 4 | H5: No | J5: Sec. 2(k), 8(5), 29 | K5: ₹250 Cr
A6: 3 | B6: GOV-003 | C6: Governance & Accountability | D6: Critical | E6: Principles Relating to Processing | F6: Are all processing activities mapped to the seven data protection principles? | G6: 1 | H6: No | J6: Sec. 4, Rules 3, 6, 8 | K6: ₹50 Cr
A7: 4 | B7: CLB-001 | C7: Consent & Lawful Basis | D7: Critical | E7: Lawful Basis for Processing | F7: Is a lawful basis documented for each processing activity (consent or legitimate use)? | G7: 0 | H7: No | J7: Sec. 4, 6, 7 | K7: ₹50 Cr
A8: 5 | B8: CLB-002 | C8: Consent & Lawful Basis | D8: Critical | E8: Valid Consent Conditions | F8: Are consent mechanisms compliant (free, specific, informed, unconditional, unambiguous)? | G8: 0 | H8: No | J8: Sec. 6, Rule 3 | K8: ₹50 Cr
A9: 6 | B9: CLB-003 | C9: Consent & Lawful Basis | D9: High | E9: Child Data Processing & Parental Consent | F9: Are age-verification and verifiable parental consent mechanisms implemented for under-18 data? | G9: 0 | H9: No | J9: Sec. 9, Rules 10-12 | K9: ₹200 Cr
A10: 7 | B10: CLB-004 | C10: Consent & Lawful Basis | D10: Low | E10: Processing Special Categories | F10: Is an inventory maintained for special-category processing with enhanced safeguards? | G10: 0 | H10: No | J10: Sec. 10 (future) | K10: ₹150 Cr
A11: 8 | B11: GOV-004 | C11: Consent & Lawful Basis | D11: Low | E11: Processing Criminal Conviction Data | F11: Is criminal data processing under official authority with documented legal basis? | G11: 0 | H11: No | J11: N/A (general) | K11: ₹50 Cr
A12: 9 | B12: GOV-005 | C12: Governance & Accountability | D12: Medium | E12: Processing Without Identification | F12: Are anonymisation techniques validated with re-identification risk assessments? | G12: 0 | H12: No | J12: Sec. 2(j), 11(2) | K12: ₹50 Cr
A13: 10 | B13: CNT-001 | C13: Consent & Notices | D13: Critical | E13: Transparency & Rights Facilitation | F13: Are standalone, plain-language notices with Rule 3 elements deployed at all points? | G13: 0 | H13: No | J13: Sec. 5, 6, Rules 3, 9, 14 | K13: ₹50 Cr
A14: 11 | B14: CNT-002 | C14: Consent & Notices | D14: Medium | E14: Information at Collection | F14: Are standalone notices issued at/before every data collection point? | G14: 0 | H14: No | J14: Sec. 5, 6, Rule 3 | K14: ₹50 Cr
A15: 12 | B15: CNT-003 | C15: Consent & Notices | D15: Medium | E15: Information — Indirect Collection | F15: Are indirect collection activities registered with notices delivered within timelines? | G15: 0 | H15: No | J15: Sec. 5, 8(1) | K15: ₹50 Cr
... A79: 76 | B79: GOV-026 | C79: Governance & Accountability | D79: Critical | E79: Enforcement & Penalties Readiness | F79: Is a penalty risk register with enforcement readiness and DPB response procedures? | G79: 0 | H79: No | J79: Sec. 18-33, Schedule | K79: ₹250 Cr
A81: ASSESSMENT SUMMARY
B83: OVERALL READINESS | F83: Score | G83: Max | H83: % Complete
B84: Overall Maturity Score | F84: =SUM(G4:G79) -> 7 | G84: =COUNTA(A4:A79)*4 -> 304 | H84: =IF(G84=0,0,F84/G84) -> 0.023026316
B85: Critical Controls Score | F85: {=SUMPRODUCT((D4:D79="Critical")*(G4:G79))} -> 7 | G85: =COUNTIF(D4:D79,"Critical")*4 -> 56 | H85: =IF(G85=0,0,F85/G85) -> 0.125
B86: High Controls Score | F86: {=SUMPRODUCT((D4:D79="High")*(G4:G79))} -> 0 | G86: =COUNTIF(D4:D79,"High")*4 -> 68 | H86: =IF(G86=0,0,F86/G86) -> 0
B87: Medium Controls Score | F87: {=SUMPRODUCT((D4:D79="Medium")*(G4:G79))} -> 0 | G87: =COUNTIF(D4:D79,"Medium")*4 -> 136 | H87: =IF(G87=0,0,F87/G87) -> 0
B88: Low Controls Score | F88: {=SUMPRODUCT((D4:D79="Low")*(G4:G79))} -> 0 | G88: =COUNTIF(D4:D79,"Low")*4 -> 44 | H88: =IF(G88=0,0,F88/G88) -> 0
B91: CATEGORY BREAKDOWN | F91: Avg Maturity | G91: Controls | H91: Evidence Ready
B92: Governance & Accountability | F92: =IFERROR(AVERAGEIF(C4:C79,"Governance & Accountability",G4:G79),0) -> 0.28 | G92: =COUNTIF(C4:C79,"Governance & Accountability") -> 25 | H92: =COUNTIFS(C4:C79,"Governance & Accountability",H4:H79,"Yes") -> 0
B93: Consent & Lawful Basis | F93: =IFERROR(AVERAGEIF(C4:C79,"Consent & Lawful Basis",G4:G79),0) -> 0 | G93: =COUNTIF(C4:C79,"Consent & Lawful Basis") -> 10 | H93: =COUNTIFS(C4:C79,"Consent & Lawful Basis",H4:H79,"Yes") -> 0
B94: Consent & Notices | F94: =IFERROR(AVERAGEIF(C4:C79,"Consent & Notices",G4:G79),0) -> 0 | G94: =COUNTIF(C4:C79,"Consent & Notices") -> 5 | H94: =COUNTIFS(C4:C79,"Consent & Notices",H4:H79,"Yes") -> 0
B95: Data Principal Rights | F95: =IFERROR(AVERAGEIF(C4:C79,"Data Principal Rights",G4:G79),0) -> 0 | G95: =COUNTIF(C4:C79,"Data Principal Rights") -> 10 | H95: =COUNTIFS(C4:C79,"Data Principal Rights",H4:H79,"Yes") -> 0
B96: Security & Safeguards | F96: =IFERROR(AVERAGEIF(C4:C79,"Security & Safeguards",G4:G79),0) -> 0 | G96: =COUNTIF(C4:C79,"Security & Safeguards") -> 3 | H96: =COUNTIFS(C4:C79,"Security & Safeguards",H4:H79,"Yes") -> 0
B97: Breach Management | F97: =IFERROR(AVERAGEIF(C4:C79,"Breach Management",G4:G79),0) -> 0 | G97: =COUNTIF(C4:C79,"Breach Management") -> 2 | H97: =COUNTIFS(C4:C79,"Breach Management",H4:H79,"Yes") -> 0
B98: Cross-Border Transfers | F98: =IFERROR(AVERAGEIF(C4:C79,"Cross-Border Transfers",G4:G79),0) -> 0 | G98: =COUNTIF(C4:C79,"Cross-Border Transfers") -> 8 | H98: =COUNTIFS(C4:C79,"Cross-Border Transfers",H4:H79,"Yes") -> 0
B99: Processors & Third Parties | F99: =IFERROR(AVERAGEIF(C4:C79,"Processors & Third Parties",G4:G79),0) -> 0 | G99: =COUNTIF(C4:C79,"Processors & Third Parties") -> 1 | H99: =COUNTIFS(C4:C79,"Processors & Third Parties",H4:H79,"Yes") -> 0
B100: Data Lifecycle Management | F100: =IFERROR(AVERAGEIF(C4:C79,"Data Lifecycle Management",G4:G79),0) -> 0 | G100: =COUNTIF(C4:C79,"Data Lifecycle Management") -> 1 | H100: =COUNTIFS(C4:C79,"Data Lifecycle Management",H4:H79,"Yes") -> 0
B101: Processing Principles | F101: =IFERROR(AVERAGEIF(C4:C79,"Processing Principles",G4:G79),0) -> 0 | G101: =COUNTIF(C4:C79,"Processing Principles") -> 6 | H101: =COUNTIFS(C4:C79,"Processing Principles",H4:H79,"Yes") -> 0
B102: Privacy Programme Mgmt | F102: =IFERROR(AVERAGEIF(C4:C79,"Privacy Programme Mgmt",G4:G79),0) -> 0 | G102: =COUNTIF(C4:C79,"Privacy Programme Mgmt") -> 5 | H102: =COUNTIFS(C4:C79,"Privacy Programme Mgmt",H4:H79,"Yes") -> 0
